{
    "video_id": "uORo0k_uuKs",
    "title": "infos",
    "description": "Soziale Netzwerke___________________________________________________\n\nTikTok:  https:\/\/www.tiktok.com\/@drachenlordrw?lang=de\n\nSpotifay: https:\/\/open.spotify.com\/artist\/32NwB52qRB6AqswORCxOpV\n\n \u25ba Danke f\u00fcrs anschauen!\n      Gru\u00df\n      Drache",
    "publish_date": "2021-02-09T13:05:00+01:00",
    "duration": "959",
    "channel_id": "UCm3_j4RLEzgMovQTRPx47MQ",
    "channel_title": "Drachen Lord",
    "comments": []
}