{
    "video_id": "pJ7ceb9faPA",
    "title": "Draches Kommends #008 Zum Reh Video",
    "description": "Kanalmitglied werden und exklusive Vorteile erhalten:\nhttps:\/\/www.youtube.com\/channel\/UCm3_j4RLEzgMovQTRPx47MQ\/join\n\nAmazon Liste:\nhttps:\/\/www.amazon.de\/hz\/wishlist\/ls\/2L8FP7DFBFEC7?ref_=wl_share\n\nSoziale Netzwerke___________________________________________________\n\nTikTok:  https:\/\/www.tiktok.com\/@drachenlordrw?lang=de\n\nTwitter https:\/\/twitter.com\/Drachen26328829\n\nSpotifay: https:\/\/open.spotify.com\/artist\/32NwB52qRB6AqswORCxOpV\n\n \u25ba Danke f\u00fcrs anschauen!\n      Gru\u00df\n      Drache",
    "publish_date": "2021-08-07T12:30:38+02:00",
    "duration": "1390",
    "channel_id": "UCm3_j4RLEzgMovQTRPx47MQ",
    "channel_title": "Drachen Lord",
    "comments": [
        {
            "comment_id": "UgxF8XDtdsBBhL6suzN4AaABAg",
            "comment_text": "1ter",
            "comment_author": "Nicht lustig tv",
            "comment_author_id": "UCO_CYtRuvJWnvls-Z5YC8vg",
            "comment_time": "2021-08-08T12:32:30+02:00"
        },
        {
            "comment_id": "Ugw3Co_JXuVjsr8FquB4AaABAg",
            "comment_text": "Endlich ist es wieder soweit! Adrenalinschub!",
            "comment_author": "Mo Bi",
            "comment_author_id": "UC1wG1xpIhdgqQQfq5swRWeg",
            "comment_time": "2021-08-08T12:32:32+02:00"
        },
        {
            "comment_id": "Ugz6msM_6rHDWxqgkVV4AaABAg",
            "comment_text": "Erster",
            "comment_author": "Novi Weiss",
            "comment_author_id": "UC1Gm-fN9rUDNs4kE3sK4TUw",
            "comment_time": "2021-08-08T12:32:38+02:00"
        },
        {
            "comment_id": "UgxvSbS8VdyNbw9AZMR4AaABAg",
            "comment_text": "21ster",
            "comment_author": "Mesa Jar Jar Binks",
            "comment_author_id": "UCLdcgWgAXu9tOluWccwefGQ",
            "comment_time": "2021-08-08T12:33:32+02:00"
        },
        {
            "comment_id": "Ugy50rX43EBME5ZCX4N4AaABAg",
            "comment_text": "Wie d\u00fcnn er da noch war",
            "comment_author": "dieser eine",
            "comment_author_id": "UCvZ3pNODJz5i3rfAj-RSsNw",
            "comment_time": "2021-08-08T12:34:10+02:00"
        },
        {
            "comment_id": "UgzAonnaIEDI5k3Xhbd4AaABAg",
            "comment_text": "Drache bro du bist mies korrekt hast dicke Eier mach weiter so",
            "comment_author": "Schmerz HD",
            "comment_author_id": "UCNTdUOju3iOyB4aEwHclO2g",
            "comment_time": "2021-08-08T12:34:12+02:00"
        },
        {
            "comment_id": "UgxHfv791vt1oCxuUC94AaABAg",
            "comment_text": "moin. ein gut gemeinter tipp von mir: das jeweilige video nochmal in der infobox verlinken. viele gr\u00fc\u00dfe",
            "comment_author": "Insho",
            "comment_author_id": "UChQY3z-razUkLj-QDu33WGg",
            "comment_time": "2021-08-08T12:34:42+02:00"
        },
        {
            "comment_id": "UgyS8fXJDqmCWsZmpZt4AaABAg",
            "comment_text": "Man kann davon ausgehen, dass sich der Oger das Kitz kurz darauf wie auch das Ei am St\u00fcck in den Rachen rutschen lassen hat.",
            "comment_author": "Bock auf Ballern",
            "comment_author_id": "UCdx6d00IOOb8gYfLq6CzhUQ",
            "comment_time": "2021-08-08T12:36:31+02:00"
        },
        {
            "comment_id": "Ugz8GCVvy0rNiHhJnTx4AaABAg",
            "comment_text": "ich bin cool",
            "comment_author": "Helge Taube",
            "comment_author_id": "UClfVgiuWBvZUi3Dd6wiV30g",
            "comment_time": "2021-08-08T12:37:09+02:00"
        },
        {
            "comment_id": "UgwCsPYF9cs7GH-K25R4AaABAg",
            "comment_text": "f\u00fcr n\u00e4chtes kommends video: wie denkst du \u00fcber die kriegsverbrechen deines vaters?",
            "comment_author": "Braiking Boss",
            "comment_author_id": "UCjyWSjQJzx8fqLrJPq9Q_yA",
            "comment_time": "2021-08-08T12:37:25+02:00"
        },
        {
            "comment_id": "UgzgZoI0iSZCN4mG2CB4AaABAg",
            "comment_text": "Danke dass du dir immer so viel M\u00fche gibst beim Rendern!",
            "comment_author": "Carlo Bubb",
            "comment_author_id": "UCDILSEnqBNzLpm6fuyGiK1Q",
            "comment_time": "2021-08-08T12:39:14+02:00"
        },
        {
            "comment_id": "UgwQ9sloeM-RKiUPAgh4AaABAg",
            "comment_text": "Safe hat er sich das Kitz reingerendert.",
            "comment_author": "Carlo Bubb",
            "comment_author_id": "UCDILSEnqBNzLpm6fuyGiK1Q",
            "comment_time": "2021-08-08T12:39:59+02:00"
        },
        {
            "comment_id": "Ugy7Uv4xLqB6GXb6qtB4AaABAg",
            "comment_text": "Dieser Idiot hat nichts verstanden ????????????????",
            "comment_author": "_testoo",
            "comment_author_id": "UCiRLHDoMCijhSgSmWD_bq5A",
            "comment_time": "2021-08-08T12:40:23+02:00"
        },
        {
            "comment_id": "UgxMRYammfk51m2wHM54AaABAg",
            "comment_text": "69ster",
            "comment_author": "MrAprilTv",
            "comment_author_id": "UCGlxTpqhyc5pk_IOqGceJtA",
            "comment_time": "2021-08-08T12:40:36+02:00"
        },
        {
            "comment_id": "UgwWPYovP6D4No_vbwt4AaABAg",
            "comment_text": "Hagebuddne",
            "comment_author": "NEWTOM",
            "comment_author_id": "UCn83ucAmXGfkaq-du_zxRpw",
            "comment_time": "2021-08-08T12:40:47+02:00"
        },
        {
            "comment_id": "UgwXtHyxzCsDgqmL0G14AaABAg",
            "comment_text": "????Schneiden rendern hochladen\nIhr untersch\u00e4tzt das immer alle????",
            "comment_author": "Baum Lutscher",
            "comment_author_id": "UCTHfYar6H1o-EBFcXyz3PDw",
            "comment_time": "2021-08-08T12:41:00+02:00"
        },
        {
            "comment_id": "UgykXTSUQPHlB1UkK654AaABAg",
            "comment_text": "Ist Barcaelon dein Lieblingslied?",
            "comment_author": "Deutsche Memes",
            "comment_author_id": "UCVqR-RejdhFBvaMstAijY-Q",
            "comment_time": "2021-08-08T12:41:28+02:00"
        },
        {
            "comment_id": "UgxGENmVQNqZgfJqlkd4AaABAg",
            "comment_text": "Habe die Fakten \u00fcber Rehkitze nach jedem Statement vom Drachen gegoogelt und sieh an, er hat bez\u00fcglich der Tarnung, dem Fluchtinstinkt und dem Geruch von Rehkitze wirklich recht. Dass ich hier mal was lerne, wer h\u00e4tte es gedacht ????????",
            "comment_author": "Mr. Gut gemeint",
            "comment_author_id": "UCTbFfyRImLCU-hmas_ty_9w",
            "comment_time": "2021-08-08T12:41:33+02:00"
        },
        {
            "comment_id": "UgwbkO-3hNrB_mCMg2R4AaABAg",
            "comment_text": "Etzatla neue Gommendare alda !",
            "comment_author": "H\u00e4uptling Kaggduschne",
            "comment_author_id": "UCTt1FnFPR8flLoZzdK2876w",
            "comment_time": "2021-08-08T12:41:58+02:00"
        },
        {
            "comment_id": "UgzSDMRO0R2M7r-pR514AaABAg",
            "comment_text": "Holt euch die Hater app!!",
            "comment_author": "Jan Ullrich",
            "comment_author_id": "UC8P9HlC-aEAmMtlzvGqLUgA",
            "comment_time": "2021-08-08T12:43:00+02:00"
        },
        {
            "comment_id": "Ugxqzbjw3ZleiW_rN2l4AaABAg",
            "comment_text": "Drache, mach weiter so. Gibt sehr viele, die dich gut finden! Finde Dich absolut sympathisch. Und das meine ich ernst!",
            "comment_author": "AFFE",
            "comment_author_id": "UCKe7-qI0FOkZSQq1KL8dJNw",
            "comment_time": "2021-08-08T12:43:57+02:00"
        },
        {
            "comment_id": "UgzmTt_vxP-YifmcQO94AaABAg",
            "comment_text": "Das Kitze keinen Eigengeruch haben wusste ich auch net. Konnte einmal eins \u00fcber ne Minute lang beobachten bevor es mich bemerkt hat und selbst dann ist es noch dageblieben. Mein Hund wollte unbedingt. Wei\u00df immernoch nicht ob er es jagen oder mit spielen wollte.",
            "comment_author": "Jack",
            "comment_author_id": "UCqqmDRg9pdQSVBfZACdyZEw",
            "comment_time": "2021-08-08T12:47:38+02:00"
        },
        {
            "comment_id": "Ugx9F7ZiKC96FXoPpTh4AaABAg",
            "comment_text": "Egal, wo ich das Video anhalte; jedes Frame ein Meme!",
            "comment_author": "Eisenherz",
            "comment_author_id": "UCWT46h-HVYOANWpRu68Nq7A",
            "comment_time": "2021-08-08T12:50:07+02:00"
        },
        {
            "comment_id": "UgwM-letzhfxQCRvTbV4AaABAg",
            "comment_text": "man hat man dir in den Kopf gepupst man xD \u00b4\u00b4Rehexperte\u00b4\u00b4",
            "comment_author": "Mega BrotAufstrich",
            "comment_author_id": "UCsjcdd4zQullbxwUzAySIlw",
            "comment_time": "2021-08-08T12:50:56+02:00"
        },
        {
            "comment_id": "UgwfPz7TZrwsjhzWzI54AaABAg",
            "comment_text": "9:30 Aahhhahahahhahahaahhhhaahahahhaa ab da hat der endg\u00fcltig mein Bauch zerfetzt",
            "comment_author": "Salah Ad-Din Al-Ayyubi",
            "comment_author_id": "UC7ZEkuWTqEPYqFQbt9NhyrQ",
            "comment_time": "2021-08-08T12:51:43+02:00"
        },
        {
            "comment_id": "UgzRqlydnJ1y-gOV-k94AaABAg",
            "comment_text": "wie riecht das alte slipknot sh\u00f6rder?",
            "comment_author": "kaliber6020",
            "comment_author_id": "UClcZ2E31r1pSedjV2OgkUDA",
            "comment_time": "2021-08-08T12:52:36+02:00"
        },
        {
            "comment_id": "UgxBrJGfKOKEKjc8fDd4AaABAg",
            "comment_text": "korregazionsgriff, alles klar",
            "comment_author": "Talvisota",
            "comment_author_id": "UCLYAFyYNHnyV9NqvBzk-0ag",
            "comment_time": "2021-08-08T12:53:28+02:00"
        },
        {
            "comment_id": "Ugx7GmQSJGLYonSdfq94AaABAg",
            "comment_text": "Der Rechtfertigungslord is wieder am wuseln und werken",
            "comment_author": "RetroReiner",
            "comment_author_id": "UCd7CUOyT5zm3xjp8jFIQnfw",
            "comment_time": "2021-08-08T12:54:20+02:00"
        },
        {
            "comment_id": "UgwE_9RcxWSnaliz5Ed4AaABAg",
            "comment_text": "Bau dir endlich eine mauer um dein Grundst\u00fcck",
            "comment_author": "geek house85",
            "comment_author_id": "UCntI6vegYL9b5saudcsiAwA",
            "comment_time": "2021-08-08T12:56:26+02:00"
        },
        {
            "comment_id": "UgzoxW_ACleO7Jq_h3t4AaABAg",
            "comment_text": "Wingele hat also im Wald gejagt.\nNa dann zeig mal deinen Jagdschein, Kollege. Oder kann man Wilderei auch zur langen Liste der unbestrafte  Gesetzesbr\u00fcche hinzuf\u00fcgen?",
            "comment_author": "Maverick",
            "comment_author_id": "UCgKsKh-6DlTCi8hB8nNnMNQ",
            "comment_time": "2021-08-08T12:56:59+02:00"
        },
        {
            "comment_id": "UgzOvi1YeAAx5wN_htp4AaABAg",
            "comment_text": "Sch\u00f6n wie er jedesmal luft holen muss, wen er was vorlessen will",
            "comment_author": "Der Eine",
            "comment_author_id": "UCKie8OfvyYj0E6TLfr2jllA",
            "comment_time": "2021-08-08T12:57:52+02:00"
        },
        {
            "comment_id": "UgypHuUDwnWOZSz5zgp4AaABAg",
            "comment_text": "Stell doch mal Kaffee und Kuchen auf f\u00fcr deine Reisegruppen, oder bist du zu arm?",
            "comment_author": "???????????????????? \u211b????????????",
            "comment_author_id": "UCAqJ_l5b74qTyll86bzYkVw",
            "comment_time": "2021-08-08T12:59:00+02:00"
        },
        {
            "comment_id": "Ugw08O4Rdsrz8-Ss05p4AaABAg",
            "comment_text": "Das sind die Verwechslungen mit Sprache der Unterschiedlichkeit wie T\u00fcrken, T\u00fcrk oder sonst was. Nicht falsch verstehen! Es geht um das Tier, das ich auch mal interessiere.",
            "comment_author": "Mercedes EQS",
            "comment_author_id": "UCpRS7NlmiaBLWlJmfUxyORw",
            "comment_time": "2021-08-08T13:02:04+02:00"
        },
        {
            "comment_id": "UgySFZ9hiTvDEADPSMl4AaABAg",
            "comment_text": "So lustig wie er erz\u00e4hlt wie die Mutter dem Reh sagt du bleibst jetzt hier etzadla bis ich widder komm ????herrlich",
            "comment_author": "Django84",
            "comment_author_id": "UCVQO8kPZs5d15I1ZFL1zCnw",
            "comment_time": "2021-08-08T13:02:49+02:00"
        },
        {
            "comment_id": "UgzUhKDwUkHopva_RHF4AaABAg",
            "comment_text": "Kann er nicht einfach die Top Kommentare kommentieren? Er nimmt immer random Kommentare",
            "comment_author": "Patti",
            "comment_author_id": "UCbSzYYAJtW3nGzIAFEk8wIQ",
            "comment_time": "2021-08-08T13:02:49+02:00"
        },
        {
            "comment_id": "Ugxp-RiD1C50hAzjbZh4AaABAg",
            "comment_text": "Wann gibst du den V\u00f6geln endlich ihr Nest zur\u00fcck?",
            "comment_author": "Exe Boss",
            "comment_author_id": "UCWfwW_syiBikh7IS5VUa5Ng",
            "comment_time": "2021-08-08T13:03:11+02:00"
        },
        {
            "comment_id": "UgwI8Z9IofCqRKFzHd14AaABAg",
            "comment_text": "13:44 Ja, ja das warst du gut erkannt",
            "comment_author": "KENNY",
            "comment_author_id": "UCzwBWtpRaJF_St83MJK4P5g",
            "comment_time": "2021-08-08T13:03:40+02:00"
        },
        {
            "comment_id": "UgxtzOWAMGx8Yzqv2vh4AaABAg",
            "comment_text": "17:42",
            "comment_author": "Salah Ad-Din Al-Ayyubi",
            "comment_author_id": "UC7ZEkuWTqEPYqFQbt9NhyrQ",
            "comment_time": "2021-08-08T13:04:04+02:00"
        },
        {
            "comment_id": "Ugwk1UGIeuSIacSrkG94AaABAg",
            "comment_text": "Wann kommt eigentlich das n\u00e4chste Video mit Ey Mallah???",
            "comment_author": "Julian Holzer",
            "comment_author_id": "UCjmIeyoFSmE1WvVEOAvYEPQ",
            "comment_time": "2021-08-08T13:04:41+02:00"
        },
        {
            "comment_id": "UgyuP8LD4NVS98Eaupl4AaABAg",
            "comment_text": "Knaststaffel ruft",
            "comment_author": "Steel mitch",
            "comment_author_id": "UCq8nIEn85xjZmB6UrfXh48Q",
            "comment_time": "2021-08-08T13:05:09+02:00"
        },
        {
            "comment_id": "Ugyf6qBzKB04GG6ghHF4AaABAg",
            "comment_text": "Einfach nur sch\u00f6n wie seine Oberlippe zuckt beim reden und sein Unterkiefer sich hervorhebt &lt;3",
            "comment_author": "Niko",
            "comment_author_id": "UCHvEJK_yXloKvAnZR6DdPWg",
            "comment_time": "2021-08-08T13:06:44+02:00"
        },
        {
            "comment_id": "Ugyforb3Y8_nTjBkYSZ4AaABAg",
            "comment_text": "Wieso muss er\/es immer so ne Fresse ziehen beim Sprechen?\nWill er damit sein geistigen Zustand unterstrichen und noch deutlicher zum Ausdruck bringen? ????",
            "comment_author": "Oh man!",
            "comment_author_id": "UCwDdN5W4xM8BWjuHgzHf-ZA",
            "comment_time": "2021-08-08T13:07:15+02:00"
        },
        {
            "comment_id": "Ugz-hPnZqgmhjStRuKt4AaABAg",
            "comment_text": "A Reh-Striemer wars Rainerlein... a Reh-Striemer",
            "comment_author": "Baohnpaohlupunadaaldreier",
            "comment_author_id": "UC1gFEYUsaV__5ehqViTYDkQ",
            "comment_time": "2021-08-08T13:08:47+02:00"
        },
        {
            "comment_id": "UgzMVYhEOw_kkbEKbi94AaABAg",
            "comment_text": "Der Mostkopp aus der Sonderschule scriemt wieder... Zu deinen Vorstellungen zu Ethik (Rehkitz) sage ich mal nichts.....",
            "comment_author": "Oliver YT",
            "comment_author_id": "UCAwqX-ZS6upLz3Z2Fha2r-Q",
            "comment_time": "2021-08-08T13:09:32+02:00"
        },
        {
            "comment_id": "UgxmrLub80DI9B-mVQh4AaABAg",
            "comment_text": "Wasch dich Mal, damit du etzedla nimmer f\u00fcr uns echsisdierst",
            "comment_author": "bleppo blepp",
            "comment_author_id": "UCbTMGwstGcmWcZqbqgxgqoA",
            "comment_time": "2021-08-08T13:10:48+02:00"
        },
        {
            "comment_id": "UgzGDyiS6g4qw3fs-7R4AaABAg",
            "comment_text": "Wenn man &quot;tierische Sachen&quot; dem J\u00e4ger \u00fcbergibt, hast du dich dann etzadla gerade zum Abschuss freigegeben..? Du bist so hohl mit deiner &quot;Dullischl\u00e4ue&quot;... Utopisch...",
            "comment_author": "Oliver YT",
            "comment_author_id": "UCAwqX-ZS6upLz3Z2Fha2r-Q",
            "comment_time": "2021-08-08T13:11:49+02:00"
        },
        {
            "comment_id": "Ugy9dDNjQC8X2MhTzbx4AaABAg",
            "comment_text": "Er kennt Claus Kleber nicht ????",
            "comment_author": "Gregor",
            "comment_author_id": "UClIY0bIPMbsBQzPxwoKG0gg",
            "comment_time": "2021-08-08T13:13:16+02:00"
        },
        {
            "comment_id": "UgyBW6SHOEKljSRqrs14AaABAg",
            "comment_text": "Du machst gerne tierische Sachen mit so nem F\u00f6rster... A gro\u00dfer Wasserf\u00f6rster",
            "comment_author": "Baohnpaohlupunadaaldreier",
            "comment_author_id": "UC1gFEYUsaV__5ehqViTYDkQ",
            "comment_time": "2021-08-08T13:14:06+02:00"
        },
        {
            "comment_id": "Ugz6fsYTVgrP1a5arc94AaABAg",
            "comment_text": "Dieses Kieferzuggne",
            "comment_author": "sundowner",
            "comment_author_id": "UCOWDYZS6hWX0ryuRpzm6lmg",
            "comment_time": "2021-08-08T13:14:26+02:00"
        },
        {
            "comment_id": "UgwiMr2op3fa6QQGTrV4AaABAg",
            "comment_text": "Nat\u00fcrlich dauert das erste Mal schlafen mit der Frau nur ein paar Sekunden, weil er nach 2 Sekunden kommt",
            "comment_author": "Gregor",
            "comment_author_id": "UClIY0bIPMbsBQzPxwoKG0gg",
            "comment_time": "2021-08-08T13:15:01+02:00"
        },
        {
            "comment_id": "UgxmEjJ3W-zUteRut9N4AaABAg",
            "comment_text": "Sucht Kommentare raus hat sie aber nicht gelesen ????",
            "comment_author": "Sergej F\u00e4hrlich",
            "comment_author_id": "UCi6Ltd2r7gSJxLU6HkyBOtg",
            "comment_time": "2021-08-08T13:17:27+02:00"
        },
        {
            "comment_id": "Ugzgsi2HbzPqvtXq-hp4AaABAg",
            "comment_text": "Du arsch,d\u00fcrftest noch nicht mal an das kitz rangehen.aber du bist top auf deinem Hof aufgehoben.super Bauer",
            "comment_author": "Matthias Kroehl",
            "comment_author_id": "UCQkh2iaHlO2B1UuNi5oDA3A",
            "comment_time": "2021-08-08T13:17:43+02:00"
        },
        {
            "comment_id": "UgxG0apJF_t2ag9jvHl4AaABAg",
            "comment_text": "Bambi mit 400gr Modsarella \u00fcberbacken.\n\nG\u00f6nn dir Speckb\u00e4r!",
            "comment_author": "Mo Bi",
            "comment_author_id": "UC1wG1xpIhdgqQQfq5swRWeg",
            "comment_time": "2021-08-08T13:24:38+02:00"
        },
        {
            "comment_id": "Ugz1eTqPZynd9neRhJ94AaABAg",
            "comment_text": "13:52 Kinderg\u00e4rtner...Kindergartenkind....H\u00e4tte aber auch Klingelst\u00e4nder sein k\u00f6nnen. Laif is Str\u00e4nscher lest gr\u00fcsne.",
            "comment_author": "JLB",
            "comment_author_id": "UC1jKrksPKpCxwAoF3fOGE9Q",
            "comment_time": "2021-08-08T13:25:15+02:00"
        },
        {
            "comment_id": "UgwBcTPv8SZLW1f0itR4AaABAg",
            "comment_text": "Wenn der Dulli die Kommentare nicht checkt. Einfach dumm wie Brot. Wechsel lieber dein Shirt.",
            "comment_author": "Bettellord",
            "comment_author_id": "UCsPiFUfLDNbDjpr-NWgDV_Q",
            "comment_time": "2021-08-08T13:30:52+02:00"
        },
        {
            "comment_id": "UgxHJCJqxX360snMeg14AaABAg",
            "comment_text": "Es ist unglaublich, das er immer noch nicht merkt, dass die Leute absichtlich aufgrund seines Dialektes so schreiben.",
            "comment_author": "Meinii",
            "comment_author_id": "UCcvAe68-ukBUOLqZkzyAw2Q",
            "comment_time": "2021-08-08T13:32:32+02:00"
        },
        {
            "comment_id": "Ugx4J3YnuyBaCPOaCih4AaABAg",
            "comment_text": "Dieser Mann ist unglaublich informiert unglaublich das er von der Sonderschule kommt.",
            "comment_author": "squall 85",
            "comment_author_id": "UCPBJBjwVmzcafmI8MHQGDPw",
            "comment_time": "2021-08-08T13:33:31+02:00"
        },
        {
            "comment_id": "UgwmhYKir4o3-vThvlV4AaABAg",
            "comment_text": "Spielt hier jemand Killing Floor ?",
            "comment_author": "Rainer_Zufall",
            "comment_author_id": "UCCCsc7aoio0YsHJM4JqRO-Q",
            "comment_time": "2021-08-08T13:33:40+02:00"
        },
        {
            "comment_id": "UgwLatzI_E_zObe7Qd94AaABAg",
            "comment_text": "Sehr geehrter Herr Winkler!\nIm Namen von ganz NRW m\u00f6chte ich mich bei ihnen bedankne. Ihr Rettungspaket ist gestern bei uns angekommne dadsechlich soga. Wir habne uns sehr \u00fcber die 600 Plastikdeckel gefreut. Durch diese selbstlose Tat ihrerseits, hoffne wir f\u00fcr sie dass der Haid etzadla wenicher wird, weil  sie sind ja nicht derjeniche der herkommt und die Scheisse baut. Wir sind der Meinung: h\u00e4tte man Amerika damals nicht entdeckt und alle Indianer umgebracht, w\u00fcrdne dort heute sowas wie Elfen lebne. Denn was braucht Nahrung um zu wachsen? Richtig, Wasser. Machne sie weiter so und bleibne sie auf ewig unbesiegt. Nochmals danke daf\u00fcr, Herr M\u00fcller...\u00e4h Winkler.\nHochachtungsvoll, Hagen Buddne.",
            "comment_author": "Hagen Buddne",
            "comment_author_id": "UCBQD3Y0My1x5BWJoYkF6tJw",
            "comment_time": "2021-08-08T13:33:42+02:00"
        },
        {
            "comment_id": "UgyeP9_Md7yeXYZaeXR4AaABAg",
            "comment_text": "DRACHE, dein unglaublichen gut geschnittenen Videos sind einfach der HAMMER! Ich  finde jedoch das du das lesen immernoch nicht sehr gut beherschst. Mfg deine Mudda",
            "comment_author": "lordlarry1",
            "comment_author_id": "UCsCo9IKEL8YdtaJ1vAu_GLQ",
            "comment_time": "2021-08-08T13:37:56+02:00"
        },
        {
            "comment_id": "UgwrfQElaCmr-l6Vei54AaABAg",
            "comment_text": "Cooles Video",
            "comment_author": "Tom Scheffel",
            "comment_author_id": "UC_3Ysi7l5e2aFw99lgCFlXg",
            "comment_time": "2021-08-08T13:41:18+02:00"
        },
        {
            "comment_id": "UgzQvZqpYJjo8Uw72LB4AaABAg",
            "comment_text": "Hey Drache hast du Bock auf ne runde Sport, habe gesehen das du \u00fcbel gut in kampfsport bist und w\u00fcrde gerne was von die lernen.  Mache auch bissl kampfsport aber bin sicher nicht so gut wie du :(",
            "comment_author": "Pete Blabla",
            "comment_author_id": "UCAVZsrBiDYK5QTc6M7OUh0w",
            "comment_time": "2021-08-08T13:41:54+02:00"
        },
        {
            "comment_id": "UgxfXFVJsEnrKVLSpG14AaABAg",
            "comment_text": "Winkla aka Rechtschreibpolizist...das die meisten mit Absicht falsch schreiben wird er wohl nie merken",
            "comment_author": "Bier\u00f6ffner",
            "comment_author_id": "UCNM7V-Gthq45xFper73A3dg",
            "comment_time": "2021-08-08T13:44:09+02:00"
        },
        {
            "comment_id": "UgzNntXv74SUcAeF_YZ4AaABAg",
            "comment_text": "Memelord rafft mal wieder gar nichts. Was eine Lachwitzfigur",
            "comment_author": "Xenomorph",
            "comment_author_id": "UCqvDYSjB2Y_mmH-KD96h3lg",
            "comment_time": "2021-08-08T13:46:35+02:00"
        },
        {
            "comment_id": "UgwyBNaxKA-2IqZxL4Z4AaABAg",
            "comment_text": "Jawohl genau so ist es.????????????????",
            "comment_author": "Andreas Jahn",
            "comment_author_id": "UCCVtXRnpA7OUMCZ1E63r2Lw",
            "comment_time": "2021-08-08T13:47:41+02:00"
        },
        {
            "comment_id": "Ugxaecblg0QKQisryIF4AaABAg",
            "comment_text": "Wie derjeniche nicht tschekt das man ihn mit dem falschschreiben verarscht",
            "comment_author": "Reiner w\u00f6nkler",
            "comment_author_id": "UCNTrMhpNc8QYuRxwANDlj3Q",
            "comment_time": "2021-08-08T13:48:28+02:00"
        },
        {
            "comment_id": "UgxBpVSOQq3m9H-lZ7p4AaABAg",
            "comment_text": "Hey Drache, wann kommt mal wieder ein Video mit B\u00e4m aller?",
            "comment_author": "1900nuller",
            "comment_author_id": "UCk9frFfi1vV6CQP2UxJoOlA",
            "comment_time": "2021-08-08T13:50:48+02:00"
        },
        {
            "comment_id": "Ugy0TSqnD7U-g8RV5wB4AaABAg",
            "comment_text": "9:09 omg ich sp\u00fcr schon widder meine Gehirnzellne absterbne",
            "comment_author": "Lina",
            "comment_author_id": "UCs0lcyZWXqek6z3v2e1M9yA",
            "comment_time": "2021-08-08T13:51:31+02:00"
        },
        {
            "comment_id": "Ugxov8i0K7tSQEaf4XZ4AaABAg",
            "comment_text": "EY MALLA",
            "comment_author": "Asobi Buddy",
            "comment_author_id": "UCU5vHoe-uewFS6AVlbSe4iA",
            "comment_time": "2021-08-08T13:51:37+02:00"
        },
        {
            "comment_id": "UgyI7mW2Nen9HxtZb7F4AaABAg",
            "comment_text": "ich hab eine ernste frage. warum musst du dich immer rechtfertigen? und vor allem warum musst du immer zwingend besser sein als andere?\n\nUnd ja evtl w\u00e4ren ein paar leute vorbei gelaufen ohne das kitz zu bemerken aber die meisten, oder ihr alle. ist so derma\u00dfen anma\u00dfend das man dich am liebsten ganz doll dr\u00fccken w\u00fcrde\n\nAuf dem dorf ist es ganz normal das man wiesen und wege kennt, die verwuchert sind. Die so alt sind das keiner mehr den ursprung kennt. die nicht mehr zu sehen sind, weil sie seit jahren oder jahrzehnten nicht mehr genutzt werden usw.",
            "comment_author": "0711 City",
            "comment_author_id": "UCXuVuaYFh_JVde3S4QnAHHw",
            "comment_time": "2021-08-08T13:51:37+02:00"
        },
        {
            "comment_id": "UgzoPQLvZ4YdXk0VNnh4AaABAg",
            "comment_text": "I love you Dragon",
            "comment_author": "Lukas",
            "comment_author_id": "UCpHbT8e8VR_kr6BdV3ZCUDg",
            "comment_time": "2021-08-08T13:52:35+02:00"
        },
        {
            "comment_id": "UgyMS3WC6xHvK5az2m54AaABAg",
            "comment_text": "Hast meine 99,99\u20ac\/mtl",
            "comment_author": "Flo G",
            "comment_author_id": "UCY98F8QZ-LW2JDhjikif7Cw",
            "comment_time": "2021-08-08T13:52:46+02:00"
        },
        {
            "comment_id": "UgyMjJPyFMfoeEOAfPN4AaABAg",
            "comment_text": "Du g\u00e4nnst das Meddlfr\u00e4ngische ganz genau, ferdammde Aggst!",
            "comment_author": "regO",
            "comment_author_id": "UCWA3z92qNgpFAxkaJ8ft_dw",
            "comment_time": "2021-08-08T13:53:32+02:00"
        },
        {
            "comment_id": "UgxeBaRraBy-JAFsIFx4AaABAg",
            "comment_text": "Wer ist der ungepflegte Nachrichtensprecher da oben? Und warum bin ich auf der Seite \u00fcber die man nicht spricht schon wieder gesperrt? Ich hol mir mal rum!",
            "comment_author": "Holger Damm",
            "comment_author_id": "UCu8SXjyXi1QWrTCACvx5FHw",
            "comment_time": "2021-08-08T13:54:06+02:00"
        },
        {
            "comment_id": "Ugw3bnjNBzgQ2m7Qi6x4AaABAg",
            "comment_text": "Ach \u00fcbrigens Santa Kino ist der uneheliche Sohn von Santa Klaus.????????????????????????",
            "comment_author": "Andreas Jahn",
            "comment_author_id": "UCCVtXRnpA7OUMCZ1E63r2Lw",
            "comment_time": "2021-08-08T13:54:17+02:00"
        },
        {
            "comment_id": "UgwCOap8lYg6jGi3nPh4AaABAg",
            "comment_text": "Hast du schon deinen sohn angerufen?",
            "comment_author": "Dennis Fab",
            "comment_author_id": "UCncZVRmuPME_-RtjWHmQMow",
            "comment_time": "2021-08-08T13:55:33+02:00"
        },
        {
            "comment_id": "Ugwp6RtC4qQ4qpc2G5t4AaABAg",
            "comment_text": "Wieso muss er seine Fresse immer so verziehen das macht unglaublich aggressiv",
            "comment_author": "Captain D",
            "comment_author_id": "UCWlp0wunzkZ3S_aQ796qdCQ",
            "comment_time": "2021-08-08T13:57:59+02:00"
        },
        {
            "comment_id": "UgxdP_ndA556-qbowpl4AaABAg",
            "comment_text": "So ein unsympathischer Mensch. H\u00e4uptling Wasserbein wei\u00df alles..",
            "comment_author": "Nold Wahoinz",
            "comment_author_id": "UCcJ2IX0XVUnlIhSw52tfOoQ",
            "comment_time": "2021-08-08T13:59:47+02:00"
        },
        {
            "comment_id": "UgwS7VVsk6eOkB5RJZh4AaABAg",
            "comment_text": "Er scheint etwas m\u00fcde zu sein. Am besten gehen ein paar Leute hin um ihn zu wecken.",
            "comment_author": "Christian",
            "comment_author_id": "UC6tDTM0VU2WhszrbEghPEbw",
            "comment_time": "2021-08-08T14:01:12+02:00"
        },
        {
            "comment_id": "UgwgK0JsdFTho-93sPh4AaABAg",
            "comment_text": "er benutzt immer noch Korregation. ick Werd nicht mehr.",
            "comment_author": "Lam1e",
            "comment_author_id": "UC-2E6oOi-9Zj4WK2zrvoaQw",
            "comment_time": "2021-08-08T14:05:59+02:00"
        },
        {
            "comment_id": "UgwdqeHsMQHS3_8R8Vd4AaABAg",
            "comment_text": "Wenn die Gesichtsspastiken kicken. Wer kennts nicht",
            "comment_author": "Steven Krieger",
            "comment_author_id": "UC-pqDyGd3G99FtCMhgBBkxA",
            "comment_time": "2021-08-08T14:07:20+02:00"
        },
        {
            "comment_id": "Ugxb6hBu9qYPEAnDYDt4AaABAg",
            "comment_text": "Haldne die hamsters noch winterschlaf WaldesLord?",
            "comment_author": "Simon",
            "comment_author_id": "UCyb1FBiE_cBrNJCLeBY45Bg",
            "comment_time": "2021-08-08T14:10:31+02:00"
        },
        {
            "comment_id": "Ugy1xazry-EJDsI0wA14AaABAg",
            "comment_text": "Die hater App ist richtig gut lohnt sich das Abo richtig",
            "comment_author": "Pascal Sx",
            "comment_author_id": "UC5WJeAvGgxU0JYxb3QdT7RQ",
            "comment_time": "2021-08-08T14:12:22+02:00"
        },
        {
            "comment_id": "Ugz_gzQl6wfGUjZh9JN4AaABAg",
            "comment_text": "unn\u00f6tig",
            "comment_author": "Animal Mother",
            "comment_author_id": "UCuFRBn7ou1kIi4JVAySqazw",
            "comment_time": "2021-08-08T14:18:26+02:00"
        },
        {
            "comment_id": "UgxIPdlpTdmQpr2f-Bp4AaABAg",
            "comment_text": "was hastn du fuer ne erziehung genossen?",
            "comment_author": "fabian saurer",
            "comment_author_id": "UCal8IeVkLhs1S2LFKtGzCQA",
            "comment_time": "2021-08-08T14:22:48+02:00"
        },
        {
            "comment_id": "Ugw-kpHZuLhpmRuSaYZ4AaABAg",
            "comment_text": "6:45 wie er sich so unfassbar besser f\u00fchlt als dieser dude. deswegen mag ihn auch keiner",
            "comment_author": "Dotscher",
            "comment_author_id": "UCExnfSl3DsN1JZVWRkji3Cg",
            "comment_time": "2021-08-08T14:22:50+02:00"
        },
        {
            "comment_id": "UgyEeSUEyOzJ9KcCPU94AaABAg",
            "comment_text": "Du warst am 01.08 geschminkt und hast noch heute die Schminke auf deinem Gesicht.. Nicht b\u00f6se gemeint, aber das ist halt echt nicht gut f\u00fcr die Poren..^^",
            "comment_author": "Billie Eilish x3",
            "comment_author_id": "UCi5pyqzpAPLPUtepEX8DJww",
            "comment_time": "2021-08-08T14:23:05+02:00"
        },
        {
            "comment_id": "Ugx2j5XKJogpmafJCeh4AaABAg",
            "comment_text": "Wie schlagfertig er damals noch war ...",
            "comment_author": "meddwurscht",
            "comment_author_id": "UC2Zr5pgHi-qdp-H9NjVU2sg",
            "comment_time": "2021-08-08T14:23:49+02:00"
        },
        {
            "comment_id": "Ugy4M5ZI7qbDUUOCUOV4AaABAg",
            "comment_text": "Du schnallst es nicht oder???? Kannst schon fast einem leid tun ????",
            "comment_author": "Ramona G",
            "comment_author_id": "UCFLzZvKoJ31ipTi7RORuWGg",
            "comment_time": "2021-08-08T14:25:37+02:00"
        },
        {
            "comment_id": "UgxF2NnfVK7Ef7Tbv-54AaABAg",
            "comment_text": "Halllllo",
            "comment_author": "sartanp 12",
            "comment_author_id": "UC0Bx6vRY1FTMuDJuKj4ahPg",
            "comment_time": "2021-08-08T14:27:08+02:00"
        },
        {
            "comment_id": "UgwrO5W8rHBosxTGwnR4AaABAg",
            "comment_text": "Legga Kackduschne",
            "comment_author": "Master Chief",
            "comment_author_id": "UC16A5UNvEQxQO4o5S-MDiiQ",
            "comment_time": "2021-08-08T14:27:19+02:00"
        },
        {
            "comment_id": "UgyspAlnblYEbfCJ2P94AaABAg",
            "comment_text": "Ich war mit drei Loiden unnerwegs...Drachengames, -Barde und joker1510? Ich meine, sonst hasst dich ja jeder.",
            "comment_author": "Wurstfachinspektor",
            "comment_author_id": "UC7f21L_F00LUXKKrFy2-VHQ",
            "comment_time": "2021-08-08T14:27:23+02:00"
        },
        {
            "comment_id": "UgwU2X0EOiIEXxsUnf14AaABAg",
            "comment_text": "Wann boxt ihm mal endlich einer die Lichter aus, hm? Am liebsten der Dude mit dem englischen Dialekt aus der Nachbarschaft?",
            "comment_author": "H.P. Hatecraft",
            "comment_author_id": "UCaQOOU5tbN3PzH9t-yv_egg",
            "comment_time": "2021-08-08T14:27:26+02:00"
        },
        {
            "comment_id": "UgwuFsfXddC2s3Tfvcp4AaABAg",
            "comment_text": "Wie er nicht checkt das wir mit der falschen schreibweise sine sprachne meinen du kaschpar",
            "comment_author": "eselmove",
            "comment_author_id": "UCcil1T0jd_W35rhBTv4SQuA",
            "comment_time": "2021-08-08T14:28:28+02:00"
        },
        {
            "comment_id": "UgxfCz4DEDVWvR9thDd4AaABAg",
            "comment_text": "4:40 schade, dass er den Corega-Tab-Griff nicht angewandt hat, um den Dirk zu grillen",
            "comment_author": "sqlars",
            "comment_author_id": "UC45CT1hD0n-Sd3rYSQlnvjg",
            "comment_time": "2021-08-08T14:29:41+02:00"
        },
        {
            "comment_id": "UgzSf4PWmrF3sENXeVR4AaABAg",
            "comment_text": "Der WaldLord hat gesprochen. Er kennt alles besser wei\u00df viel mehr als der durchschnittliche Zuschauer aber bei der Flutkatastrophe muss er sich erst Informieren. \n\nEr ist sein Lebenlang im Wald aufgewachsen. \n\nMade my Day",
            "comment_author": "Psychomilhouse",
            "comment_author_id": "UCr8w868wjYqdrRSrUw3268w",
            "comment_time": "2021-08-08T14:30:29+02:00"
        },
        {
            "comment_id": "UgxD94-GiehW-ZZmrb54AaABAg",
            "comment_text": "zu doof um die Kommentare zu checken die ihm mit der Rechtschreibung bzw. Aussprache verarschen",
            "comment_author": "cooler mann",
            "comment_author_id": "UC7G_K-oPyZyqlunlwh7S6Ow",
            "comment_time": "2021-08-08T14:31:51+02:00"
        },
        {
            "comment_id": "Ugzktpobul583a9pvI94AaABAg",
            "comment_text": "wenn schon die gesamte youtubewelt nichts mit dir zu tun haben will, waere es schon wenn du den richter fuer das jubilaeum an start bekommst",
            "comment_author": "fabian saurer",
            "comment_author_id": "UCal8IeVkLhs1S2LFKtGzCQA",
            "comment_time": "2021-08-08T14:32:31+02:00"
        },
        {
            "comment_id": "UgwHPA5R1N1sTHjJ4Kx4AaABAg",
            "comment_text": "Rudiausbuddelne",
            "comment_author": "Charlie Harper",
            "comment_author_id": "UCJRznrNfVlE1dtw5wowvYUA",
            "comment_time": "2021-08-08T14:32:37+02:00"
        },
        {
            "comment_id": "UgzilzrU82gypESAsGd4AaABAg",
            "comment_text": "&quot;Das ist kein Reh, das ist ein Kitz.&quot; ......... Man kennt es: Erst frisst das Kitz sehr viele Bl\u00e4tter, dann kriecht es einen Baum hoch, verpuppt sich und dann schl\u00fcpft ein Reh.",
            "comment_author": "MrZillas",
            "comment_author_id": "UCtfLaAne3ihCP1DArK_kKOw",
            "comment_time": "2021-08-08T14:36:15+02:00"
        },
        {
            "comment_id": "UgzP_NlIgY-lwE2LYu14AaABAg",
            "comment_text": "also alleine die ersten 5 minuten sind halt einfach wieder mal der unwiderlegbare beweis daf\u00fcr, dass du der mit abstand d\u00fcmmste mensch der welt bist",
            "comment_author": "hey sup",
            "comment_author_id": "UCNe2vNO-ls-gpO9_FJseQpA",
            "comment_time": "2021-08-08T14:37:00+02:00"
        },
        {
            "comment_id": "UgxuOKfpV2YTlRkFiYt4AaABAg",
            "comment_text": "Bei 1:55 eingeschlafen.. und bei 23:10 aufgewacht ????",
            "comment_author": "Captain Morgan CM",
            "comment_author_id": "UCCRK7-329QpVGV6sAOBq8IQ",
            "comment_time": "2021-08-08T14:44:19+02:00"
        },
        {
            "comment_id": "UgwTFaBM58XaCLxhsOB4AaABAg",
            "comment_text": "L\u00fcgen muss man k\u00f6nnen, und Du kannst es einfach nicht. Du hast es noch nie gekonnt, meinst aber gleichzeitig, hier alle gro\u00dfartig &quot;manipulieren&quot; zu k\u00f6nnen. Du absoluter Clown.",
            "comment_author": "Leopard Prince",
            "comment_author_id": "UCXIP7MMMl0TJUl4yNpJlm-Q",
            "comment_time": "2021-08-08T14:44:20+02:00"
        },
        {
            "comment_id": "Ugz3fgitI6JwHKF89E94AaABAg",
            "comment_text": "16:12 alles Momende die der Buttergolem nie erfahren wird. Redet aber dr\u00fcbba wie n Eggsperde. Klassischer Wongel",
            "comment_author": "Robsn",
            "comment_author_id": "UCLKsuU_WAMcYOKfo-mPs3-Q",
            "comment_time": "2021-08-08T14:46:46+02:00"
        },
        {
            "comment_id": "UgxVN6eH9xhrDibT8c54AaABAg",
            "comment_text": "Die sch\u00f6nsten Momente im Leben wie zB der erste Kuss mit der Freundin, der erste Beischlaf mit der Frau, wenn man das erste mal sein Kind auf dem Arm h\u00e4lt...wirst du nie erleben, du gro\u00dfer Jutubb Star.",
            "comment_author": "Wurstfachinspektor",
            "comment_author_id": "UC7f21L_F00LUXKKrFy2-VHQ",
            "comment_time": "2021-08-08T14:47:02+02:00"
        },
        {
            "comment_id": "UgyVNwCTd49jNpJbDup4AaABAg",
            "comment_text": "Korregationsgriff - ist das Kampfsport?",
            "comment_author": "Ezio \u00c4",
            "comment_author_id": "UCXmjcmWiGhko1F7VHKrPnIw",
            "comment_time": "2021-08-08T14:51:18+02:00"
        },
        {
            "comment_id": "Ugzk3sObp150ZBLBNYF4AaABAg",
            "comment_text": "be\u00e4ngstigend, wie man hier sieht, was passiert, wenn man das baby wegschmei\u00dft und die nachgeburt gro\u00dfzieht...(gemeint ist nicht das reh)... so ein gscheiterle...oder um es auf fr\u00e4nkisch zu formulieren: \nhaab mer den dappn zam jetzetla? odder soll ich na allaans freckt hau awail???",
            "comment_author": "Berry J. Jules",
            "comment_author_id": "UCUYKFCDgHMXXhFhfMKGLlJA",
            "comment_time": "2021-08-08T15:01:13+02:00"
        },
        {
            "comment_id": "UgzFSge_TWwvv9nSjPp4AaABAg",
            "comment_text": "Naja......das Rehkitz ist unsichtbar und riecht nach nichts. Der Oger ignoriert die Realit\u00e4t und mieft stark. So unterschiedlich sind die Lebewesneee.",
            "comment_author": "Sehr Fraglich (!?)",
            "comment_author_id": "UCcQq15XJJtPNFNPXqY_otkw",
            "comment_time": "2021-08-08T15:10:09+02:00"
        },
        {
            "comment_id": "UgwZg9oLhIW7iWAj9DV4AaABAg",
            "comment_text": "Was er schon wieder f\u00fcr M\u00fcll redet. Ich kann nicht mehr????????????",
            "comment_author": "Max",
            "comment_author_id": "UC421pcuZYP4_PR5HdE_lLew",
            "comment_time": "2021-08-08T15:24:32+02:00"
        },
        {
            "comment_id": "UgyzsZKU5SgswRqEdpR4AaABAg",
            "comment_text": "So nen cringer m\u00fcll",
            "comment_author": "Max",
            "comment_author_id": "UC421pcuZYP4_PR5HdE_lLew",
            "comment_time": "2021-08-08T15:28:24+02:00"
        },
        {
            "comment_id": "UgxnLIoNGwSljYos7qF4AaABAg",
            "comment_text": "Ja wir schreiben so weil wir dich Vollidiot mimen",
            "comment_author": "Hagen",
            "comment_author_id": "UCABXPGMtrdBr-TOHWiith3g",
            "comment_time": "2021-08-08T15:29:44+02:00"
        },
        {
            "comment_id": "UgwjU7-J7L8YmB2vPpN4AaABAg",
            "comment_text": "Brojeggd Brode un Br\u00f6dchne hnausschmaisen etzala aba soford!!1",
            "comment_author": "Brombeer Bomber",
            "comment_author_id": "UCtCOZlaVc1-xizBOzZdi6dQ",
            "comment_time": "2021-08-08T15:45:46+02:00"
        },
        {
            "comment_id": "UgwIkFuJjHUpOjkvyex4AaABAg",
            "comment_text": "Kommends waaaaaaaaaaaaas",
            "comment_author": "TheDonchr1s",
            "comment_author_id": "UC5rSACEhe5fyMMUNffE-IoA",
            "comment_time": "2021-08-08T15:46:34+02:00"
        },
        {
            "comment_id": "UgzV3Ml_5ncGGaPCAt94AaABAg",
            "comment_text": "Was f\u00fcr ein Vollidiot",
            "comment_author": "Martin Steiner",
            "comment_author_id": "UCahZPvGgvksrPgDuWmeMC2g",
            "comment_time": "2021-08-08T15:47:54+02:00"
        },
        {
            "comment_id": "UgxNj73enOZGMfSQoiN4AaABAg",
            "comment_text": "Hast du es gegessen?",
            "comment_author": "Psychologin Haider",
            "comment_author_id": "UCXFJCSsh9gYCJpmIhxUnciw",
            "comment_time": "2021-08-08T15:58:12+02:00"
        },
        {
            "comment_id": "Ugwyo9jEztmImW3eaV94AaABAg",
            "comment_text": "Er checkt nach 10j hate dat wir det bewussr machne um ihne verwirrene",
            "comment_author": "Psychologin Haider",
            "comment_author_id": "UCXFJCSsh9gYCJpmIhxUnciw",
            "comment_time": "2021-08-08T16:02:23+02:00"
        },
        {
            "comment_id": "UgzMMGifHww_nXPX-Vl4AaABAg",
            "comment_text": "An ein Rehkitz kommt man sogar recht nah dran, denn die verstecken sich und kommen nicht aus ihrem Versteck. Auch die Mutter ist h\u00f6chstens 30-60 min am Tag \u00fcberhaupt bei ihrem Kitz damit das Versteck geheim bleibt.",
            "comment_author": "Thiahen Atre'Idis",
            "comment_author_id": "UCgI_q-lPVt1XpOxWsoJ_dSA",
            "comment_time": "2021-08-08T16:06:58+02:00"
        },
        {
            "comment_id": "UgxD48suUAYupKwSSg94AaABAg",
            "comment_text": "Was soll der J\u00e4ger denn machen? Nichts, denn der darf in der Jagdsaison jagen aber sonst darf der nichts. Der F\u00f6rster war schon ganz richtig.",
            "comment_author": "Thiahen Atre'Idis",
            "comment_author_id": "UCgI_q-lPVt1XpOxWsoJ_dSA",
            "comment_time": "2021-08-08T16:07:32+02:00"
        },
        {
            "comment_id": "UgzRdif8X4wmgUMl-lp4AaABAg",
            "comment_text": "Der COPDlord vor\/nach jeden Satz am erstickne",
            "comment_author": "Miss Marple",
            "comment_author_id": "UClXwxi0S2A7kBrCz0aD3EBw",
            "comment_time": "2021-08-08T16:19:04+02:00"
        },
        {
            "comment_id": "Ugw9qtm-iS87DPvWafh4AaABAg",
            "comment_text": "L ooo L du und LAUFEN .... OMG FETT bewegt sich dann nur. Du und LESEN! Einfach zu Bl\u00f6d zum LESEN!",
            "comment_author": "Gerhard Zimmermann",
            "comment_author_id": "UClPo22_pIrvLnkWQHvLb3aw",
            "comment_time": "2021-08-08T16:23:03+02:00"
        },
        {
            "comment_id": "Ugy4XSxwo0g74JSI5MJ4AaABAg",
            "comment_text": "H\u00f6r auf!",
            "comment_author": "doc2nerd",
            "comment_author_id": "UCMG0puYxAnSS5vnQpfezrEw",
            "comment_time": "2021-08-08T16:24:42+02:00"
        },
        {
            "comment_id": "UgxmWhzmAJdrREfdSJJ4AaABAg",
            "comment_text": "Meddel on",
            "comment_author": "skydrow 1-0",
            "comment_author_id": "UCSUQAxqBKP8-1NZufFSdoLw",
            "comment_time": "2021-08-08T16:32:18+02:00"
        },
        {
            "comment_id": "UgxvOv2RSQ4dCbHubT94AaABAg",
            "comment_text": "Etzala die Baby-Reh-Tarnung dads\u00e4chlich soga",
            "comment_author": "SenpaiFirestorm - osu! Map Showcase",
            "comment_author_id": "UCIoCj-ZklVixCHiJnh2FF4Q",
            "comment_time": "2021-08-08T16:33:55+02:00"
        },
        {
            "comment_id": "Ugx8SQOp5EJiFxWkB7N4AaABAg",
            "comment_text": "Typ wir schreiben so wie du redest ^^",
            "comment_author": "Ach ja",
            "comment_author_id": "UCBXA06gmBk1M-rnr6o_fO-g",
            "comment_time": "2021-08-08T16:36:45+02:00"
        },
        {
            "comment_id": "UgzwEzpt-E-gKhmVtVV4AaABAg",
            "comment_text": "Das arme reh.",
            "comment_author": "Niko Wasgehtsiedasan",
            "comment_author_id": "UCANaMkIuUkep5EhIyitSb4g",
            "comment_time": "2021-08-08T16:57:09+02:00"
        },
        {
            "comment_id": "UgyQX97h7EwsSF4beTd4AaABAg",
            "comment_text": "Ruhe sonst gibts Br\u00fcggl du dicke Lordschaft",
            "comment_author": "Moms_Spaghetti55",
            "comment_author_id": "UC8ghBkiKI67AUxF-A_qDssg",
            "comment_time": "2021-08-08T16:58:46+02:00"
        },
        {
            "comment_id": "UgyeTEjFVkL51jGyCtt4AaABAg",
            "comment_text": "Kleines Rehkitz gesehen,voll lecker!",
            "comment_author": "Freddy Kr\u00fcger",
            "comment_author_id": "UCTiQioGTllGjdtagUUIDaJQ",
            "comment_time": "2021-08-08T16:59:21+02:00"
        },
        {
            "comment_id": "Ugxyi3XeXA2d-QeZtax4AaABAg",
            "comment_text": "Versteht er einfach nicht, dass diese falsche Schreibweise beabsichtigt ist ?",
            "comment_author": "Nagi",
            "comment_author_id": "UCwk1VyBSBDwo8xOTPoOIBDw",
            "comment_time": "2021-08-08T16:59:28+02:00"
        },
        {
            "comment_id": "UgzaVNp2RVoo9lAGOTR4AaABAg",
            "comment_text": "Das Rehkitz, selten wie schwarze materie",
            "comment_author": "Li Sa",
            "comment_author_id": "UC8w6K7Q6cDTnOkGG3Sp57_w",
            "comment_time": "2021-08-08T17:06:22+02:00"
        },
        {
            "comment_id": "UgyTOAXaFPRPnFvbtj54AaABAg",
            "comment_text": "Imagine die Kommentare mal einblenden.",
            "comment_author": "Nagi",
            "comment_author_id": "UCwk1VyBSBDwo8xOTPoOIBDw",
            "comment_time": "2021-08-08T17:08:02+02:00"
        },
        {
            "comment_id": "Ugz7hDlxSh61hibiXaJ4AaABAg",
            "comment_text": "Was ein vollidiot der macht das doch bestimmt extra tanzverbot like so dumm kann der nicht sein",
            "comment_author": "Luca",
            "comment_author_id": "UCfNL4AFQi0afEhxrnr1Tp2A",
            "comment_time": "2021-08-08T17:10:20+02:00"
        },
        {
            "comment_id": "UgwxHDTUXJZln57BPBp4AaABAg",
            "comment_text": "Wann rufst du deinen Sohn endlich an?",
            "comment_author": "Anabolek",
            "comment_author_id": "UCOS-1fkaiJfSIJ2Dgav5m_Q",
            "comment_time": "2021-08-08T17:13:36+02:00"
        },
        {
            "comment_id": "Ugwc2OTyuf8S3bd-NTF4AaABAg",
            "comment_text": "Macht jeden Kommentarschreiber dumm an, weil sie absichtlich falsch schreiben\n\nMeme\n\n4:53 Sagt seit Jahren &quot;Korregation&quot; und peilt nicht, dass es das Wort nicht gibt",
            "comment_author": "made",
            "comment_author_id": "UCDIHx_sLgJE-oaNwEzsdaPg",
            "comment_time": "2021-08-08T17:18:33+02:00"
        },
        {
            "comment_id": "Ugy4Zm-Z2WbN40S73gd4AaABAg",
            "comment_text": "Er kriegt viel mehr als die meisten mit, wenn er unterwegs ist. Winglers Augen sind einfach \u00fcberall, tads\u00e4chlich sogar.",
            "comment_author": "DarkNight5560",
            "comment_author_id": "UCaaE5Q3whaKa-opy7wtMQYg",
            "comment_time": "2021-08-08T17:21:28+02:00"
        },
        {
            "comment_id": "UgyJdmcLe7xU7OlmzwV4AaABAg",
            "comment_text": "Ne Eymallah Staffel w\u00e4re echt ne nice Sache!",
            "comment_author": "Hans Pansen",
            "comment_author_id": "UCrg3EEnZ4u_KA3KLzczsQQw",
            "comment_time": "2021-08-08T17:27:54+02:00"
        },
        {
            "comment_id": "Ugyxgq0nGeSOYTClMwl4AaABAg",
            "comment_text": "mach mal ein H\u00f6rbuch :)",
            "comment_author": "Hitcher",
            "comment_author_id": "UCZXvxD4adVQeRYo3vsJD5zA",
            "comment_time": "2021-08-08T17:30:06+02:00"
        },
        {
            "comment_id": "UgwU-OLTKQIlAfQr_aF4AaABAg",
            "comment_text": "QUALIT\u00c4TSFORMAT :)",
            "comment_author": "yagashiu Pe",
            "comment_author_id": "UC8kEdOWk4YpqlzxB9P7mliw",
            "comment_time": "2021-08-08T17:35:44+02:00"
        },
        {
            "comment_id": "UgyMII4NBk9IRmn7U8p4AaABAg",
            "comment_text": "&quot;Wer kennt nichts, mit 3 Leuten 30 Minuten spazieren&quot; =)",
            "comment_author": "yagashiu Pe",
            "comment_author_id": "UC8kEdOWk4YpqlzxB9P7mliw",
            "comment_time": "2021-08-08T17:37:46+02:00"
        },
        {
            "comment_id": "UgyhQt7GEK3yU9Y39fJ4AaABAg",
            "comment_text": "laufen aha",
            "comment_author": "Alex Miller",
            "comment_author_id": "UC5DhqhYRuEuGRgPPHqYfMxA",
            "comment_time": "2021-08-08T17:40:34+02:00"
        },
        {
            "comment_id": "UgxSzfJM2_f29bHDcu94AaABAg",
            "comment_text": "Folge mit EyMallah w\u00e4re echt der Hammer ????",
            "comment_author": "minz geschmack",
            "comment_author_id": "UCByPhT--iST4wsKa2Ih_j3Q",
            "comment_time": "2021-08-08T17:47:31+02:00"
        },
        {
            "comment_id": "UgynY5_7fgMOpP81ym94AaABAg",
            "comment_text": "Bald..bald wanderst du Verbrecher endlich in den Knast",
            "comment_author": "Retsch Martin",
            "comment_author_id": "UCDJTd6QgC1WCiB4jgJCNaXQ",
            "comment_time": "2021-08-08T17:49:20+02:00"
        },
        {
            "comment_id": "UgyoR6rjGI3DCad4yf94AaABAg",
            "comment_text": "Die Pseudo-Weisheiten und die Jagd\/Waldbelehrungen sind mal wieder \u00e4u\u00dferst sinnfrei und grunds\u00e4tzlich schwachsinnig. Gudes Fideo, Wingl.",
            "comment_author": "Stuka",
            "comment_author_id": "UCXpcRmfXIdjnjg2CCDnRwOA",
            "comment_time": "2021-08-08T17:50:42+02:00"
        },
        {
            "comment_id": "Ugyd3Ei5JnWAgIEgzSV4AaABAg",
            "comment_text": "Du hast Angst vor dem Metzger gib es zu",
            "comment_author": "M.M",
            "comment_author_id": "UCb76yZRi-RTseoqdWRRPOtg",
            "comment_time": "2021-08-08T17:50:58+02:00"
        },
        {
            "comment_id": "UgwuHlFsFR0NIn-pdtp4AaABAg",
            "comment_text": "wie war es eigentlich schon mit 4 Jahren im Wald mit deim Vadder zu sein?",
            "comment_author": "Tierpfleger Altschauerberg",
            "comment_author_id": "UCKuSov7PwnknqqgmF_uvI9A",
            "comment_time": "2021-08-08T18:03:30+02:00"
        },
        {
            "comment_id": "Ugy7mB18ubruM5XAjxl4AaABAg",
            "comment_text": "ALSO REYNAR DU BIST ECHT EIN GANZ BESONDERER MENSCH...",
            "comment_author": "\u03beV\u0131\u2514 \u03c2\u0131\u2514\u2261nZ ????????",
            "comment_author_id": "UCpwTmQg7ckLSfKg6ZUcbzZw",
            "comment_time": "2021-08-08T18:04:58+02:00"
        },
        {
            "comment_id": "UgxmZwTu6IzBRxtCQ3N4AaABAg",
            "comment_text": "Ein L\u00fcgenfeuerwerk",
            "comment_author": "dan1el",
            "comment_author_id": "UCBh7C4pl2vJ4sNO8BwY9UWQ",
            "comment_time": "2021-08-08T18:09:53+02:00"
        },
        {
            "comment_id": "UgwAxgErOAuy5vHD1iR4AaABAg",
            "comment_text": "lass endlich die Katze von dem Nachbar aus deinem Keller !!!",
            "comment_author": "Tierpfleger Altschauerberg",
            "comment_author_id": "UCKuSov7PwnknqqgmF_uvI9A",
            "comment_time": "2021-08-08T18:14:36+02:00"
        },
        {
            "comment_id": "Ugy06yulW9-rvnPdqvp4AaABAg",
            "comment_text": "direkt aufn grill metalt",
            "comment_author": "Augie_ 516",
            "comment_author_id": "UCE5mzGYwUyR0Dr3NgOAUZ_w",
            "comment_time": "2021-08-08T18:15:59+02:00"
        },
        {
            "comment_id": "Ugy0PTXUFMl-el-PSgF4AaABAg",
            "comment_text": "Die Kommendare waren \u00fcberall sehr doggsisch, weil alle sich voll einb\u00fcldne zu wissn was ma Sache is!",
            "comment_author": "Alf92",
            "comment_author_id": "UC9CzSnyiWMqIkvv43MwiOzQ",
            "comment_time": "2021-08-08T18:23:53+02:00"
        },
        {
            "comment_id": "Ugz0jhfuX0EpEpC6bfd4AaABAg",
            "comment_text": "Das mit dem F\u00f6rster bescheid sagen ist absolut richtig. Da musst du nicht so bl\u00f6d tun du Mostkopp. Du hast doch von absolut nichts eine Ahnung.",
            "comment_author": "Einheimischer",
            "comment_author_id": "UCHMlRbsCDt_aiidMF6pJWGw",
            "comment_time": "2021-08-08T18:26:52+02:00"
        },
        {
            "comment_id": "Ugzz4qLiNJSHqeJhHpF4AaABAg",
            "comment_text": "Was er da noch sch\u00f6nes Schamhaar auf dem Kopf hatte...",
            "comment_author": "LOrD niBbLeR",
            "comment_author_id": "UC5ZueEuRuZID6dJ8mGi4eEw",
            "comment_time": "2021-08-08T18:45:26+02:00"
        },
        {
            "comment_id": "UgxxVDlvZ3JvL3yy-Rh4AaABAg",
            "comment_text": "Mit offenen Augen durch die Welt laufen. So nennt man Pok\u00e9mon Go also heute.",
            "comment_author": "Hoiskipoiski",
            "comment_author_id": "UCGa41rMuG7IpDd5EIDSAA3g",
            "comment_time": "2021-08-08T18:54:57+02:00"
        },
        {
            "comment_id": "UgzmgXe2Ksr7nrPlVbZ4AaABAg",
            "comment_text": "???? Er sagt selbst 3-5 mal Reh Baby und erst sp\u00e4ter Kitz und die anderen sind dumm wenn sie es falsch schreiben ????",
            "comment_author": "Noir Horo",
            "comment_author_id": "UCVV0mh_tHbRwxjCtb_k90AQ",
            "comment_time": "2021-08-08T18:55:48+02:00"
        },
        {
            "comment_id": "UgyZguKGkP4ZLDqxN0N4AaABAg",
            "comment_text": "Ich frag mich gerade ob du auf Droge bist..du sagst du warst mit Leuten unterwegs..aber es war niemand weiter zusehen..zu bl\u00f6d zum Schreiben sagt der richtige???????? UNBESIGT ????????..Eh Mallah",
            "comment_author": "Retsch Martin",
            "comment_author_id": "UCDJTd6QgC1WCiB4jgJCNaXQ",
            "comment_time": "2021-08-08T19:01:21+02:00"
        },
        {
            "comment_id": "Ugznk71-Nl1XbLkyy0F4AaABAg",
            "comment_text": "Hier k\u00f6nnte Ihre Werbung stehen!",
            "comment_author": "Druid Boy",
            "comment_author_id": "UC44jh1LKV7kLbnIBNRNjmcw",
            "comment_time": "2021-08-08T19:05:31+02:00"
        },
        {
            "comment_id": "UgzMCx6PhqPViMZ4UVp4AaABAg",
            "comment_text": "Wie man an den Kommentaren merkt, sind die M\u00f6chtegernhater vom Video wieder begeistert ???????? Das gibt Klicks und fews ???????? \nMan merkt in den Kommentaren einfach immer, wie dumm die sind ????????",
            "comment_author": "Lu. Na.",
            "comment_author_id": "UCRhtRjzKnBCBSdF07gB4LTA",
            "comment_time": "2021-08-08T19:07:12+02:00"
        },
        {
            "comment_id": "UgxEojdyg7qLDpJu07B4AaABAg",
            "comment_text": "er regt sich \u00fcber rechtschreibung von anderen auf, muss aber erstmal 1cm vorn monitor r\u00fccken um zu erkennen ob das ein d oder ein t ist",
            "comment_author": "alban ier",
            "comment_author_id": "UCPMNFyuDo-8iXiw_HI3aOgw",
            "comment_time": "2021-08-08T19:24:37+02:00"
        },
        {
            "comment_id": "Ugwpd2iN05WX2XJ0bNd4AaABAg",
            "comment_text": "10:07 neee es hat Winterschlaf gehaltne",
            "comment_author": "xXsadowXx",
            "comment_author_id": "UCbkbtyzevebC9BxOL5EuZMA",
            "comment_time": "2021-08-08T19:29:12+02:00"
        },
        {
            "comment_id": "UgxAGHHJ3d88VclrV3Z4AaABAg",
            "comment_text": "\u201eIch bin mein Leben lang in Wald aufgewachsen\u201c\nEr schafft es sich auf so vielen Ebenen zu blamieren, einfach unfassbar ????????",
            "comment_author": "Max Kleinr",
            "comment_author_id": "UCRSu47igbqITjy1dMpSIACw",
            "comment_time": "2021-08-08T19:37:06+02:00"
        },
        {
            "comment_id": "Ugyoit09RH9jlBhRiN14AaABAg",
            "comment_text": "Lord du bist der beste! bleib wie du bist &lt;3",
            "comment_author": "Mr. Noobo",
            "comment_author_id": "UCIR58MPHJ1NMRGzgXy6Su6w",
            "comment_time": "2021-08-08T19:37:25+02:00"
        },
        {
            "comment_id": "Ugw_-2funAYL60VIIxp4AaABAg",
            "comment_text": "klar war der sein leben lang im wald unterwegs, auf der suche nach artgenossen :P",
            "comment_author": "Dussy Pestroyer",
            "comment_author_id": "UCHftld_HdJu0Ab7cXMLiRfg",
            "comment_time": "2021-08-08T19:42:15+02:00"
        },
        {
            "comment_id": "UgyPOiBvSG1hOuggG1R4AaABAg",
            "comment_text": "junge junge junge",
            "comment_author": "Markus Mitteregger",
            "comment_author_id": "UCDlvpW-Tl76oaYXWOWfNB1g",
            "comment_time": "2021-08-08T19:44:09+02:00"
        },
        {
            "comment_id": "UgyINm38IBoyCb2RqRd4AaABAg",
            "comment_text": "Hr. Winklaaa...ihre zahlenden Abbonenten sind jetzt alle vollj\u00e4hrig geworden und verlangen ihr Geld zur\u00fcck. Bitte melden sie sich bei ihrer zust\u00e4ndigen Polizeistelle.",
            "comment_author": "WernerBrutzke",
            "comment_author_id": "UC8HUSwlfyiOD0kMo2EiMwGQ",
            "comment_time": "2021-08-08T19:54:30+02:00"
        },
        {
            "comment_id": "UgwB5DF1jmkahNdazGF4AaABAg",
            "comment_text": "Ich-bin-wieder-besser-Lord",
            "comment_author": "blo b",
            "comment_author_id": "UClySo3BFAgZXBsFUV_SuCGw",
            "comment_time": "2021-08-08T19:56:49+02:00"
        },
        {
            "comment_id": "Ugxb8GoqUV-y0iIcBDp4AaABAg",
            "comment_text": "Deine super Augen sind was ganz besonders.",
            "comment_author": "SadSeal",
            "comment_author_id": "UCYPSCfEaNDnpumQ-4N3AFSg",
            "comment_time": "2021-08-08T20:06:36+02:00"
        },
        {
            "comment_id": "Ugzc0SfCCi_-t4_W-7h4AaABAg",
            "comment_text": "Nur f\u00fcr die die es ni wissn.... Ein rehkids verl\u00e4sst sich immer zu 100 brozent auf seine Tarnung!",
            "comment_author": "Daniel Wende",
            "comment_author_id": "UCTwd9yH3DZkAYLGQBlANbhA",
            "comment_time": "2021-08-08T20:08:36+02:00"
        },
        {
            "comment_id": "Ugx3W8v4YDZW4AnbWy94AaABAg",
            "comment_text": "Immer noch keine Zahnb\u00fcrstne im Haus...",
            "comment_author": "Butscher",
            "comment_author_id": "UCjA0zLC9gXebMHhXPomqruw",
            "comment_time": "2021-08-08T20:16:13+02:00"
        },
        {
            "comment_id": "Ugxj0kPD9i4m7vLvtT94AaABAg",
            "comment_text": "K\u00f6nntest du mal Hunt: Showdown zocken?",
            "comment_author": "Lorenz Stadler",
            "comment_author_id": "UCbguk8-t8LuBiD2FwYJXoqA",
            "comment_time": "2021-08-08T20:20:28+02:00"
        },
        {
            "comment_id": "UgycRGXP9bWyGxYqGgp4AaABAg",
            "comment_text": "Es gibt Online Kurse wo man lesen lernen kann.",
            "comment_author": "Mike",
            "comment_author_id": "UCtqn06Sv5WEiEmJO7jCghyQ",
            "comment_time": "2021-08-08T20:32:56+02:00"
        },
        {
            "comment_id": "UgxZgBS61t8i2ugnmgF4AaABAg",
            "comment_text": "Warum bekommst du immer Gesichtskirmes, wenn du dich beim Vorlesen \u00fcberlegen f\u00fchlst?",
            "comment_author": "Martin Meier",
            "comment_author_id": "UCUS8U7n4vyAT-RnaUnsecFA",
            "comment_time": "2021-08-08T20:49:02+02:00"
        },
        {
            "comment_id": "UgxWP8ACg5ZlQZEjICp4AaABAg",
            "comment_text": "Wie er sich in seiner Paranoia immer schon im Vorfeld rechtfertigt und entschuldigt. Wie die deutsche Regierung",
            "comment_author": "sabufaction",
            "comment_author_id": "UCzw0by03s_jMHrl6EObcR9g",
            "comment_time": "2021-08-08T21:24:19+02:00"
        },
        {
            "comment_id": "Ugzec9qJlVQCOGvZP2J4AaABAg",
            "comment_text": "Dier schreibt man mit D seit es Meddlfr\u00e4nkisch gibt",
            "comment_author": "Green Lee",
            "comment_author_id": "UCodfFYm6wA36iNC-gfbstsA",
            "comment_time": "2021-08-08T21:26:13+02:00"
        },
        {
            "comment_id": "Ugy6QTbONi0pE_eHT_R4AaABAg",
            "comment_text": "Tiersachen macht man mitm J\u00e4ger,nicht mit dem F\u00f6rster",
            "comment_author": "Christian K.",
            "comment_author_id": "UCrMoghJn9GdfW0_jy8_QqQA",
            "comment_time": "2021-08-08T21:41:53+02:00"
        },
        {
            "comment_id": "UgyDE3m2L-7YPW2Jb_R4AaABAg",
            "comment_text": "Meine Anmerkung, dass du das Video vom Format &quot;Rehkitzrettung im Morgengrauen&quot; geklaut hast, wurde nat\u00fcrlich ignoriert. Und dieser Kommentar hatte das vorgeschriebene Format von zwei Zeilen.",
            "comment_author": "Old Wankerhand",
            "comment_author_id": "UCiTmfuuO0uVCq_eZar0fVcg",
            "comment_time": "2021-08-08T21:43:13+02:00"
        },
        {
            "comment_id": "UgzQA28y9HMJ0Va-1VR4AaABAg",
            "comment_text": "werbunglord",
            "comment_author": "Kreuzfahrer EL SID",
            "comment_author_id": "UCl5EwhiTc_XRW8F8Zk836BQ",
            "comment_time": "2021-08-08T22:14:39+02:00"
        },
        {
            "comment_id": "UgyvTH7gTHEjlUmI0Bp4AaABAg",
            "comment_text": "Und btw in welcher Scheinwelt lebst du?",
            "comment_author": "Rudolf Winkler",
            "comment_author_id": "UCDd3fENeIKItO4BIahYln2w",
            "comment_time": "2021-08-08T22:17:54+02:00"
        },
        {
            "comment_id": "Ugz3Qn4iPuw96ySHt-N4AaABAg",
            "comment_text": "Er ist einfach der Tarzan aus Mittelfranken.",
            "comment_author": "Psyme",
            "comment_author_id": "UCok0rnqL6I9An1QNPkk4OSA",
            "comment_time": "2021-08-08T22:22:24+02:00"
        },
        {
            "comment_id": "UgxU4HbiSeuX39y9eg54AaABAg",
            "comment_text": "Mit Audi \u00fcberfahren und dann Bild gemacht",
            "comment_author": "xGTA1995",
            "comment_author_id": "UCX8c1LeXXlOZF1pLdaBoX0g",
            "comment_time": "2021-08-08T22:26:35+02:00"
        },
        {
            "comment_id": "Ugyima4-J167qDCm-jl4AaABAg",
            "comment_text": "Ein wahrer Naturbursche mit ca 300kg auf den Ribben!",
            "comment_author": "LUIS TODO",
            "comment_author_id": "UCDp-28f6F3s7IO_OcfmcK2A",
            "comment_time": "2021-08-08T22:26:35+02:00"
        },
        {
            "comment_id": "Ugx3joqujK6NTdwHfK54AaABAg",
            "comment_text": "Pack mal auf deine Amazon Liste ein paar Caps hinzu!!!",
            "comment_author": "Rudolf Winkler",
            "comment_author_id": "UCDd3fENeIKItO4BIahYln2w",
            "comment_time": "2021-08-08T22:34:27+02:00"
        },
        {
            "comment_id": "UgzUkZ2Nf9y2SmU8MUB4AaABAg",
            "comment_text": "Imagen meine Kommentare l\u00f6schen",
            "comment_author": "Rudolf Winkler",
            "comment_author_id": "UCDd3fENeIKItO4BIahYln2w",
            "comment_time": "2021-08-08T22:37:47+02:00"
        },
        {
            "comment_id": "UgwAfvGviVJnOAWwhvF4AaABAg",
            "comment_text": "Drache du kleiner Feigling",
            "comment_author": "Rudolf Winkler",
            "comment_author_id": "UCDd3fENeIKItO4BIahYln2w",
            "comment_time": "2021-08-08T22:38:07+02:00"
        },
        {
            "comment_id": "UgwVVseVPS5fkCFqlhB4AaABAg",
            "comment_text": "Wie stehst du zu einer Impfpflicht?",
            "comment_author": "Aerys II. Targaryen",
            "comment_author_id": "UCn1YcJJH_XLUfzV9AiwXcTA",
            "comment_time": "2021-08-08T22:38:48+02:00"
        },
        {
            "comment_id": "UgxNZC9MY8nt82TsfuV4AaABAg",
            "comment_text": "Wie findest du kpop?",
            "comment_author": "Rudolf Winkler",
            "comment_author_id": "UCDd3fENeIKItO4BIahYln2w",
            "comment_time": "2021-08-08T22:40:25+02:00"
        },
        {
            "comment_id": "UgyuJKYEFMawgRFdbcF4AaABAg",
            "comment_text": "ich habe Kriegsverbrechen in der Soviet Union getrieben",
            "comment_author": "Rudolf Winkler",
            "comment_author_id": "UCDd3fENeIKItO4BIahYln2w",
            "comment_time": "2021-08-08T22:40:47+02:00"
        },
        {
            "comment_id": "UgxKe2WdGN8epBWWtl94AaABAg",
            "comment_text": "Spielst du Killing Floor 2?",
            "comment_author": "Rudolf Winkler",
            "comment_author_id": "UCDd3fENeIKItO4BIahYln2w",
            "comment_time": "2021-08-08T22:43:31+02:00"
        },
        {
            "comment_id": "UgzMJ1U_bkCjx8F9SCF4AaABAg",
            "comment_text": "Schaiss Fidio. G\u00e4h Kaggduschne. HAGGEBUDDNE\u00c4",
            "comment_author": "Rainer Winkler",
            "comment_author_id": "UCNfHDIlDiBT1nQRIIpZFhzw",
            "comment_time": "2021-08-08T22:44:46+02:00"
        },
        {
            "comment_id": "UgxkPJPA9o1rPKg9MgZ4AaABAg",
            "comment_text": "Bin etzadla im Wald aufgwachsn ihr kagghaider",
            "comment_author": "Ma Ka",
            "comment_author_id": "UCMM9ivUPEOkxtgsBQlzoVrg",
            "comment_time": "2021-08-08T22:49:09+02:00"
        },
        {
            "comment_id": "Ugzb4v-zy83CcLgBPi14AaABAg",
            "comment_text": "Ab welcher Gr\u00f6\u00dfe z\u00e4hlt ein Wassertier als gro\u00df?",
            "comment_author": "High Star",
            "comment_author_id": "UC-UWNt9N99kkSRRPLQhHoMw",
            "comment_time": "2021-08-08T22:50:40+02:00"
        },
        {
            "comment_id": "Ugx2dUt9Hzq_vfnd76d4AaABAg",
            "comment_text": "Ein meddlnder Beddler aus Meddlfranken",
            "comment_author": "Konstantin Melber",
            "comment_author_id": "UCVSS-EK65KhUF6pRGNurldg",
            "comment_time": "2021-08-08T22:52:30+02:00"
        },
        {
            "comment_id": "UgzAxcGsCOUoMwPzMtt4AaABAg",
            "comment_text": "3:55 da kann wohl jemand nicht die oger Sprache",
            "comment_author": "High Star",
            "comment_author_id": "UC-UWNt9N99kkSRRPLQhHoMw",
            "comment_time": "2021-08-08T22:58:55+02:00"
        },
        {
            "comment_id": "UgxTQ8UiRyHkpH_LjxF4AaABAg",
            "comment_text": "Krass \nKein Tier ist vor seinem Schlund sicher \nOger frisst Bambi morgne in der Zeitung sogah",
            "comment_author": "Rainer br\u00fcllt sich in die Rente",
            "comment_author_id": "UCTF1fWX5yZfk8P6lozM-tHQ",
            "comment_time": "2021-08-08T22:59:39+02:00"
        },
        {
            "comment_id": "UgwTrA3iaef9utzSvmZ4AaABAg",
            "comment_text": "Das einzige, was du wissen tust\nIst dass du dick bist",
            "comment_author": "Rainer br\u00fcllt sich in die Rente",
            "comment_author_id": "UCTF1fWX5yZfk8P6lozM-tHQ",
            "comment_time": "2021-08-08T23:01:14+02:00"
        },
        {
            "comment_id": "UgwGyHm7M-hoIAbaz2d4AaABAg",
            "comment_text": "&quot;Man meddelt nix aufn Grill&quot;\n\nIm Dudne steht aber: Das figgdive Verb &quot;meddeln&quot; kann als Ersatz f\u00fcr alle real existierenden Verbne verwendet werden. Insbesondere in Verbindung mit Kommentaren zu Fideos vom Drachenlord ist ein h\u00e4ufiger Gebrauch zu beobachten.\n\nZum Beispiel:\nEr isst Mozareller.\n&gt; Er meddelt sich Mozareller rein.\n\nEr f\u00e4hrt zum Rewe. \n&gt; Er meddelt zum Rewe.\n\nEr streicht das Zimmer.\n&gt; Er meddelt Farbe an die Wand.",
            "comment_author": "mvri87",
            "comment_author_id": "UCelZj1-DRxJtC0DjjpR5mZQ",
            "comment_time": "2021-08-08T23:13:11+02:00"
        },
        {
            "comment_id": "UgyxOY0AsVHEmkgF-514AaABAg",
            "comment_text": "ALDA WAS IS DES SCHO WIDDER F\u00dcR A SCHEI\u00df",
            "comment_author": "Highest Wesen of the Welt",
            "comment_author_id": "UCqytmB8RBQjz4ydEBE98wog",
            "comment_time": "2021-08-08T23:33:22+02:00"
        },
        {
            "comment_id": "UgyugcOGV8aEactpGr54AaABAg",
            "comment_text": "IS BAMBI AUCH EIN WASSERTIER?",
            "comment_author": "Highest Wesen of the Welt",
            "comment_author_id": "UCqytmB8RBQjz4ydEBE98wog",
            "comment_time": "2021-08-08T23:34:57+02:00"
        },
        {
            "comment_id": "UgzT2r3ZKNiIKUsu3j54AaABAg",
            "comment_text": "Das solche Leute heutzutage nicht mehr aus der Gemeinde gejagt werden oder in den Knast kommen als Konsequenz f\u00fcr ihr Handeln, ist ein Problem unserer inkonsequenten Gesellschaft.",
            "comment_author": "maximilian Szczesny",
            "comment_author_id": "UCNs9PUAg-gnQ1NZ057y153A",
            "comment_time": "2021-08-08T23:50:04+02:00"
        },
        {
            "comment_id": "UgwMjlDxytXWbf9bH494AaABAg",
            "comment_text": "Alter was er labert",
            "comment_author": "Likwal Mohammed",
            "comment_author_id": "UCo_Dyc8eyz7aslvDKYX11Fw",
            "comment_time": "2021-08-08T23:58:43+02:00"
        },
        {
            "comment_id": "Ugwoxzuwa8XWVuQlGip4AaABAg",
            "comment_text": "ziemlich cringe w\u00fcrde ich sagen",
            "comment_author": "d beezyboy",
            "comment_author_id": "UCQKByMIPxai2pS2jh6VvTIA",
            "comment_time": "2021-08-09T00:04:11+02:00"
        },
        {
            "comment_id": "Ugym9MbLmBgM_zELy7p4AaABAg",
            "comment_text": "Ahnung von allem, Schlumpfhausen brauch Schlaubischlumpf wieder Drachenschlumpf ist gefeuert!!!",
            "comment_author": "Flummy Tommy",
            "comment_author_id": "UCAooy6wTQjbfEeIpuWkLGGA",
            "comment_time": "2021-08-09T01:12:09+02:00"
        },
        {
            "comment_id": "UgwqwA2saDP9F8ggDwF4AaABAg",
            "comment_text": "R\u00e4h naigsch\u00fcat",
            "comment_author": "Bierprofi",
            "comment_author_id": "UCGbljZSdBgnzoaRQr0b03IQ",
            "comment_time": "2021-08-09T01:19:09+02:00"
        },
        {
            "comment_id": "Ugz4Few9f-NRdhTBZf54AaABAg",
            "comment_text": "Vlog #47 ich bin spazieren gewesen ihn deinem Vlog war nie die Rede das Leute dabei waren!! Was ein Schw\u00e4tzer",
            "comment_author": "Viktor Lajkler",
            "comment_author_id": "UC3B8mfxpTDS9pKBrUw0DwHQ",
            "comment_time": "2021-08-09T02:05:59+02:00"
        },
        {
            "comment_id": "UgwrZGbqKseSed_AfE14AaABAg",
            "comment_text": "Mach mal wieder was mit xxl dildos",
            "comment_author": "Darkwing Duck",
            "comment_author_id": "UCGk0HZ2sGEECH2mlOAEKvYw",
            "comment_time": "2021-08-09T02:06:30+02:00"
        },
        {
            "comment_id": "UgxtMOS78H0oyn4TIrd4AaABAg",
            "comment_text": "Ich als Bayer muss sagen das dein bayrisch einfach zum kotzen ist etzella",
            "comment_author": "VollzeitMeddler",
            "comment_author_id": "UCuTjCY7hRe3CfTErHGjUgAw",
            "comment_time": "2021-08-09T02:08:34+02:00"
        },
        {
            "comment_id": "UgyBDt-B09ftEn0rPeR4AaABAg",
            "comment_text": "Forza Drache du alter Damhirsch!",
            "comment_author": "Elias",
            "comment_author_id": "UCyn4P-WgQKumuiXdFwpPYXw",
            "comment_time": "2021-08-09T02:17:47+02:00"
        },
        {
            "comment_id": "Ugz1ANEkK7KyDnZAjlZ4AaABAg",
            "comment_text": "Nice",
            "comment_author": "Allesandro Queensborough",
            "comment_author_id": "UCVIL2pojKN5iH5fFoEf7awg",
            "comment_time": "2021-08-09T03:17:06+02:00"
        },
        {
            "comment_id": "UgyxEQNGrkQPJCT5arF4AaABAg",
            "comment_text": "Die Drachis \u00fcbernehmen die Weltherrschaft",
            "comment_author": "Torres119 xx",
            "comment_author_id": "UCIcj8K2M4_8jMPQI-y8mdzw",
            "comment_time": "2021-08-09T03:32:43+02:00"
        },
        {
            "comment_id": "UgzRFB98n99Hw6-yz4R4AaABAg",
            "comment_text": "Kommt zu mir wenn ihr euch traut!!",
            "comment_author": "Denis Hohmann",
            "comment_author_id": "UCRvplvTSv2t4-lWpYrYbc0Q",
            "comment_time": "2021-08-09T04:58:30+02:00"
        },
        {
            "comment_id": "UgxpGM6D9YckcFFRezJ4AaABAg",
            "comment_text": "junge du geh\u00f6rst hinter den gittern",
            "comment_author": "egon kowalski",
            "comment_author_id": "UCR5guPwcJG4PjNJ_oIP6knQ",
            "comment_time": "2021-08-09T06:21:30+02:00"
        },
        {
            "comment_id": "UgyXxPruV0dmzRUwtq14AaABAg",
            "comment_text": "Au",
            "comment_author": "Mr.Kangoo",
            "comment_author_id": "UCVqR6bBucaEMrHHq1_hMhxg",
            "comment_time": "2021-08-09T06:21:50+02:00"
        },
        {
            "comment_id": "UgzEmUNXtCSfofGcXY14AaABAg",
            "comment_text": "Naturlord",
            "comment_author": "Der Echte",
            "comment_author_id": "UCggn3yWbhbfg43FPOymH1xg",
            "comment_time": "2021-08-09T06:34:24+02:00"
        },
        {
            "comment_id": "UgxTaXFWKGWdLTaNrrh4AaABAg",
            "comment_text": "er sieht richtig gut aus, der neue S\u00e4nger von Ooomph!",
            "comment_author": "Tina Lorenzo",
            "comment_author_id": "UCMTBBcVtrpr6WKybyrgYI1w",
            "comment_time": "2021-08-09T07:26:31+02:00"
        },
        {
            "comment_id": "UgwGpDk6J7VkHVU68Xl4AaABAg",
            "comment_text": "Du Oger kommst doch net mal am Tor vorbei, bei dem st\u00e4ndigen Besuch (der wichtig und richtig ist) also lass mal die M\u00e4rchenstunde stecken und bring mal wieder BRODDE UND BR\u00d6DDCHEN!",
            "comment_author": "Luca Elias",
            "comment_author_id": "UCqwaB_3v4nqYkZInq6s0QTw",
            "comment_time": "2021-08-09T07:38:29+02:00"
        },
        {
            "comment_id": "UgwK17d_MPdOhdIIXHx4AaABAg",
            "comment_text": "Modsereller",
            "comment_author": "Der einzig wahre Ulf",
            "comment_author_id": "UCsrpueSjrSveH2Bz7oWKJDQ",
            "comment_time": "2021-08-09T08:47:56+02:00"
        },
        {
            "comment_id": "UgyJCQ_N7Z2aMvmM2nt4AaABAg",
            "comment_text": "EyMalla, ein Mann voller Stolz und Ehre",
            "comment_author": "Der einzig wahre Ulf",
            "comment_author_id": "UCsrpueSjrSveH2Bz7oWKJDQ",
            "comment_time": "2021-08-09T09:07:13+02:00"
        },
        {
            "comment_id": "UgyjxDLLUMBzWIjKyhl4AaABAg",
            "comment_text": "Ey mallah",
            "comment_author": "Derkapit\u00e4nzursee",
            "comment_author_id": "UCeZUFpXV9Rfc-Od-G6NMYxA",
            "comment_time": "2021-08-09T09:41:23+02:00"
        },
        {
            "comment_id": "UgwwHqLJZzbx4jzPMt94AaABAg",
            "comment_text": "Das wird dein Jahr! Vollzug so auch kommen kann du Betrueger.",
            "comment_author": "Sigmund Adler",
            "comment_author_id": "UC0Bv2UATh8YA_mdRypDUHVg",
            "comment_time": "2021-08-09T09:55:37+02:00"
        },
        {
            "comment_id": "UgyZAWV4ZV5puDJ9_l14AaABAg",
            "comment_text": "HEUTE  geht es zur Drachenchance \nWer kommt mit ? Gibt auch Brot ???? ???? Bier und Tanzeinlagen. Lg",
            "comment_author": "Bobby Tick",
            "comment_author_id": "UCn_XWttSfzSz3nB_SozYnPA",
            "comment_time": "2021-08-09T10:52:55+02:00"
        },
        {
            "comment_id": "UgzJvGr9LcfkyA-R3454AaABAg",
            "comment_text": "Hast du das Rehkitz mit ordentlich Federdeckeln beschenkt?",
            "comment_author": "MystikoSadhana",
            "comment_author_id": "UC-bLF6qViOSplkJKdNE2I5g",
            "comment_time": "2021-08-09T11:06:36+02:00"
        },
        {
            "comment_id": "Ugy-ez3fwrrOnlfGHtR4AaABAg",
            "comment_text": "Plot twist: er hat das Kitz gegessen.",
            "comment_author": "phpp erino",
            "comment_author_id": "UCigiTDWCS7PgSgvqheh3NQw",
            "comment_time": "2021-08-09T11:22:31+02:00"
        },
        {
            "comment_id": "UgzpTpv01gnhsWe_CAZ4AaABAg",
            "comment_text": "Entweder neigfreysed oder ihr wissd scho hihihi",
            "comment_author": "MystikoSadhana",
            "comment_author_id": "UC-bLF6qViOSplkJKdNE2I5g",
            "comment_time": "2021-08-09T11:24:58+02:00"
        },
        {
            "comment_id": "UgwtRiuPlydCgw4zFC14AaABAg",
            "comment_text": "Verdammt noch mal, wie viel Grad hat es, etzatla!",
            "comment_author": "c K",
            "comment_author_id": "UCoIgelQawBhoIcdYtIbZ6BQ",
            "comment_time": "2021-08-09T11:26:32+02:00"
        },
        {
            "comment_id": "Ugzlkps6c5QCerAVdVF4AaABAg",
            "comment_text": "Schweinchen Schlau wei\u00df nat\u00fcrlich wieder alles besser ????",
            "comment_author": "Fabian",
            "comment_author_id": "UCgb-UWuwjTX0r0w9GmxNYJQ",
            "comment_time": "2021-08-09T11:55:11+02:00"
        },
        {
            "comment_id": "Ugz0zgRzR54ur4C-EXB4AaABAg",
            "comment_text": "Drachenlord kommentiert Kommentare - Baraka Edition",
            "comment_author": "BabylonWillFall",
            "comment_author_id": "UCiwi3g4WNJLztpU17Ckon_w",
            "comment_time": "2021-08-09T12:05:57+02:00"
        },
        {
            "comment_id": "UgztNByst6M5FFCJCjR4AaABAg",
            "comment_text": "stell dir vor du machst start stop onetake videos, die du von der kamera ziehst und dann direkt hochl\u00e4dst, aber st\u00e4ndig mit ernsten gesicht in die kamera sagst... jetzt wartet viel schneide- und renderarbeit auf mich. ????????",
            "comment_author": "VanniME",
            "comment_author_id": "UCIczRZOeaa6Rt9nug7UR4Jw",
            "comment_time": "2021-08-09T12:15:09+02:00"
        },
        {
            "comment_id": "UgyqR1rT1rODcPhPg_x4AaABAg",
            "comment_text": "Die existieren nicht als Geruch",
            "comment_author": "Josef Hirschenmaier",
            "comment_author_id": "UC9Hlrz9VkavAB7egwfyf-kw",
            "comment_time": "2021-08-09T12:18:04+02:00"
        },
        {
            "comment_id": "UgwH5jAh6BEWtEZr2014AaABAg",
            "comment_text": "Kein Wunder, dass es in letzter Zeit so viele Sichtungen eines entsetzlich stinkenden Bigfoots im Wald von Emskirchen gab\u2026",
            "comment_author": "Colin H",
            "comment_author_id": "UCCdL6ZdSCLpQkCG0JAGB3sg",
            "comment_time": "2021-08-09T12:21:15+02:00"
        },
        {
            "comment_id": "UgxotdVGS2PCwTLJWwh4AaABAg",
            "comment_text": "jaja wenn der j\u00e4ger wieder seine nase in den wald geht und wildtiere erschn\u00fcffelt ....",
            "comment_author": "BuganderVII",
            "comment_author_id": "UCpBjVj8DQvbSha4dS1j6Lfw",
            "comment_time": "2021-08-09T12:23:38+02:00"
        },
        {
            "comment_id": "UgzvSVVKfMXA11s5w1F4AaABAg",
            "comment_text": "Ein &quot;kurrigationsgriff&quot; ist aucht echt mal von n\u00f6ten!!!  ...diese Linguistikvandalen!!!",
            "comment_author": "ThinkUpOut",
            "comment_author_id": "UCyzLb0x3EPGPlD02_OKq_0w",
            "comment_time": "2021-08-09T12:35:27+02:00"
        },
        {
            "comment_id": "UgxRkesGyDK7-5ileCZ4AaABAg",
            "comment_text": "Es ist einfach nur unglaublich peinlich wie er versucht witzig zu sein. Ich sch\u00e4m mich richtig fremd????",
            "comment_author": "AGirlHasNoName1996",
            "comment_author_id": "UC9kOcXcNutxnVkxt1sQqj_g",
            "comment_time": "2021-08-09T12:52:25+02:00"
        },
        {
            "comment_id": "Ugxboyv2Q14RCWcF4714AaABAg",
            "comment_text": "vor 3-4 Jahren hat er dabei noch gestanden und die Kommentare eingeblendet und humoristisch reagiert. jetzt einfach nur noch tote langeweile und faulheit",
            "comment_author": "Phantron",
            "comment_author_id": "UCijf3PCDPHGURdsiH6ZlwhQ",
            "comment_time": "2021-08-09T13:28:30+02:00"
        },
        {
            "comment_id": "Ugwobe1rlvQueebBEpp4AaABAg",
            "comment_text": "In der manischen Phase ist er so viel hassenswerter.",
            "comment_author": "Nick Baumann",
            "comment_author_id": "UC8H45dyGZX878RJy8z5Lfig",
            "comment_time": "2021-08-09T14:24:16+02:00"
        },
        {
            "comment_id": "Ugz5MCluP0xJm3IOhYJ4AaABAg",
            "comment_text": "Ruf doch mal Leute zum spenden auf! Hast doch knapp 150k Abos. brickstory hat 160k und hat \u00fcber 10000\u20ac zusammenbekommen. Du interessierst dich eben nicht f\u00fcr andere. Laberst aber die hater h\u00e4tten keine Empathie. Verlogenes St\u00fcck Schei\u00dfe. Weil f\u00fcr dich nix dabei rumkommt, ist es dir egal. H\u00f6r auf dich immer rauszureden. Nutz deine \u201eGr\u00f6\u00dfe\u201c auf YouTube doch mal f\u00fcr was gutes",
            "comment_author": "TheOnes O",
            "comment_author_id": "UCBvzKQfmvIYbB6LnjgO5vHw",
            "comment_time": "2021-08-09T14:24:33+02:00"
        },
        {
            "comment_id": "UgxV-keEFKNRfpEo0FJ4AaABAg",
            "comment_text": "Junge, der hat das Verhalten der Rehe sehr gut gegooglet! Der Wald-Oger hat sich &quot;tads\u00e4chlich soga&quot; f\u00fcr sein Video vorbereitet..... zumindest zum klugscheissen :D",
            "comment_author": "MC HuMs",
            "comment_author_id": "UCPG2XentbD-3T1F3OXK0PDw",
            "comment_time": "2021-08-09T14:30:22+02:00"
        },
        {
            "comment_id": "UgwWiyh5daWMZv55daR4AaABAg",
            "comment_text": "Wirklich krass wie d\u00fcnn er da noch war",
            "comment_author": "Darth Kronos",
            "comment_author_id": "UCHM5KFidhiJIG7U6dY5VLZA",
            "comment_time": "2021-08-09T14:52:53+02:00"
        },
        {
            "comment_id": "Ugyrj024EFKLPLvz9kJ4AaABAg",
            "comment_text": "Du bist kein Bauer \nKann jeder Bauer in Emskirchen best\u00e4tigen",
            "comment_author": "Rainer br\u00fcllt sich in die Rente",
            "comment_author_id": "UCTF1fWX5yZfk8P6lozM-tHQ",
            "comment_time": "2021-08-09T15:23:01+02:00"
        },
        {
            "comment_id": "Ugz0vON_An4G0ym_gL94AaABAg",
            "comment_text": "Er hat es NICHT schnell gesagt \nDie erste Silbe totaaaaal lang gezogen \n&quot; Eeeeeeeeeee   Malla &quot;",
            "comment_author": "Rainer br\u00fcllt sich in die Rente",
            "comment_author_id": "UCTF1fWX5yZfk8P6lozM-tHQ",
            "comment_time": "2021-08-09T15:24:42+02:00"
        },
        {
            "comment_id": "UgzkoX4Lvpy6K5nv-Md4AaABAg",
            "comment_text": "dass es das Wort Korregation nicht gibt, hat er immer noch nicht gepeilt",
            "comment_author": "Anybody",
            "comment_author_id": "UCn5iN-UJN_fsj5z3cTtdogQ",
            "comment_time": "2021-08-09T16:11:27+02:00"
        },
        {
            "comment_id": "UgxFaWqKw_kVrzZEelF4AaABAg",
            "comment_text": "Ey Mallah!",
            "comment_author": "Tsaqu Amnesia",
            "comment_author_id": "UCtn7pKXd6qED7Y-z3-wJNvQ",
            "comment_time": "2021-08-09T17:26:16+02:00"
        },
        {
            "comment_id": "UgzB_GCvDYmHDfy1Zl94AaABAg",
            "comment_text": "NEW KIDZ",
            "comment_author": "Hauptteil",
            "comment_author_id": "UC5OV4oICmGeP6aH2ygxYcJQ",
            "comment_time": "2021-08-09T18:14:01+02:00"
        },
        {
            "comment_id": "UgypkpVEpZV19fcVbfN4AaABAg",
            "comment_text": "Ich liebe es: Beschwerst dich \u00fcber die Rechtschreibung anderer,aber schreibst das Wort &quot;Kommends&quot; mal komplett falsch.\n\nMan sollte nicht mit Steinen werfen,wenn man im Glashaus sitzt.",
            "comment_author": "Sin Cara",
            "comment_author_id": "UCBfwUJwxyr92-L7-a5Bfp3g",
            "comment_time": "2021-08-09T18:34:45+02:00"
        },
        {
            "comment_id": "Ugz7_qO_18hCA6UZEN94AaABAg",
            "comment_text": "&quot;Rehkinder existieren nicht als Geruch&quot;\n\nJetzt hab ich alles geh\u00f6rt...",
            "comment_author": "Ahab Duennschitz",
            "comment_author_id": "UClNiaWQ_YGxSwC1StaGX8JA",
            "comment_time": "2021-08-09T19:41:31+02:00"
        },
        {
            "comment_id": "UgwxZQ3jXOP_fnHq8Jh4AaABAg",
            "comment_text": "Macht mit LRS einen auf Grammatiklord",
            "comment_author": "Rainer Wongler",
            "comment_author_id": "UCwTGWCYb5ITODmoF0wXpE9g",
            "comment_time": "2021-08-09T19:55:43+02:00"
        },
        {
            "comment_id": "Ugzt6_h7Rr1PYnRJ8CF4AaABAg",
            "comment_text": "Gibts mal wieder ne roomtour oder Haus uptade? :)",
            "comment_author": "ItzXShadoXZy -",
            "comment_author_id": "UChiuK7EPPGMAfAOh6O6N5Mg",
            "comment_time": "2021-08-09T20:57:23+02:00"
        },
        {
            "comment_id": "UgzUllQiKRw6ZS7F6_B4AaABAg",
            "comment_text": "Wie Gesund er aussieht",
            "comment_author": "Paul Klee",
            "comment_author_id": "UCFaeZsXqag_VAKjzYhaTrOw",
            "comment_time": "2021-08-09T21:13:08+02:00"
        },
        {
            "comment_id": "UgybrtYEKgBTGJ_kvi94AaABAg",
            "comment_text": "Er muss ein Koregationsgriff machen .....l\u00e4cherlich",
            "comment_author": "nicht derjenige",
            "comment_author_id": "UC9XEiMNDUO7DCu--1ZPykdw",
            "comment_time": "2021-08-09T21:46:02+02:00"
        },
        {
            "comment_id": "UgyErzXVTGGbln8bJIp4AaABAg",
            "comment_text": "Junge ist dieses Wesen d\u00e4mlich!",
            "comment_author": "JabbOMotherfuckO",
            "comment_author_id": "UC1NuZhBd2Cg9pNB3dSm8X6A",
            "comment_time": "2021-08-10T01:36:57+02:00"
        },
        {
            "comment_id": "UgzFBA0SY9nbnyJ_Mgh4AaABAg",
            "comment_text": "9:14 \n\nDas erkl\u00e4rt so einiges",
            "comment_author": "OG 67",
            "comment_author_id": "UC6n0_RBPYNYYOpCjRFWghHQ",
            "comment_time": "2021-08-10T02:53:51+02:00"
        },
        {
            "comment_id": "Ugys_BzBxanqdEaW2bp4AaABAg",
            "comment_text": "&quot; Einen kleinen Korregazionsgriff machen &quot; und dabei andere niedermachen. Der spinnt der Schanzenmeister. Und f\u00fcr Dich Reinerle braucht man zwei J\u00e4ger. Einen f\u00fcrs Fett und einen f\u00fcr den D\u00fcnnschiss, den Du t\u00e4glich verzapfst.",
            "comment_author": "Meteo Shark",
            "comment_author_id": "UCTL1UCsP5-TJOA7MdM14nxQ",
            "comment_time": "2021-08-10T03:27:54+02:00"
        },
        {
            "comment_id": "UgwdsHR6hbCBMtQFRrp4AaABAg",
            "comment_text": "Gr\u00fc\u00dfe gehen raus an King Arschfick",
            "comment_author": "Fiko Fiko",
            "comment_author_id": "UC9atiKILWW_OblVEZn3dTQg",
            "comment_time": "2021-08-10T10:30:03+02:00"
        },
        {
            "comment_id": "UgzyXDbEPwvm_-665Mh4AaABAg",
            "comment_text": "3 Leute er und seine 2 Freundinnen !????????",
            "comment_author": "alen koldzic",
            "comment_author_id": "UC1WNVSxDKfB4uZfitzipwjQ",
            "comment_time": "2021-08-10T11:03:37+02:00"
        },
        {
            "comment_id": "UgwsEW1Qn6lZErzGE0Z4AaABAg",
            "comment_text": "J\u00e4gerlord",
            "comment_author": "Clemens Controlletti",
            "comment_author_id": "UCxlOzUjD09SM61KNf7qidaA",
            "comment_time": "2021-08-10T19:11:09+02:00"
        },
        {
            "comment_id": "Ugxrsyh0bmhYIJWpGfZ4AaABAg",
            "comment_text": "*Korregation*",
            "comment_author": "Rnezto",
            "comment_author_id": "UCxGGGgpLI6wpD1hMLcv8RPA",
            "comment_time": "2021-08-11T00:05:41+02:00"
        },
        {
            "comment_id": "UgyRMgqKlqfRJDsM5Ot4AaABAg",
            "comment_text": "&quot;ich bin mein lebenlang im wald&quot; sieht man ;3",
            "comment_author": "Saap",
            "comment_author_id": "UCf80aWo7D6mM85Q7-9BGTHw",
            "comment_time": "2021-08-11T01:41:29+02:00"
        },
        {
            "comment_id": "Ugw392qVll3KVkJbz5l4AaABAg",
            "comment_text": "werden einfach meine kommis gel\u00f6scht bin jz tlaulig das du nicht mit der wahrheit klar kommst",
            "comment_author": "Saap",
            "comment_author_id": "UCf80aWo7D6mM85Q7-9BGTHw",
            "comment_time": "2021-08-11T01:42:16+02:00"
        },
        {
            "comment_id": "UgyRNH0aPpcVqEzLMTR4AaABAg",
            "comment_text": "Also was das mit J\u00e4ger F\u00f6rster angeht und mit dem das Rehe Fluchttiere sind aber Kitze nicht da hat er schon recht",
            "comment_author": "Timo Jjj",
            "comment_author_id": "UCtuVLBnfxPmE_BzuSl-XEcg",
            "comment_time": "2021-08-11T06:53:51+02:00"
        },
        {
            "comment_id": "Ugz0UakBS-5CStfTakx4AaABAg",
            "comment_text": "Wie er meint mit seinem Adler Blick das Reh gesehen zu haben, du hast beim Wongeln einfach nur nach unten geschaut weil du fix und fertig warst der Rest geradeaus ganz einfach",
            "comment_author": "SoHaTutorials",
            "comment_author_id": "UC892_z6oQu0O0MuUT7z7hug",
            "comment_time": "2021-08-14T22:48:10+02:00"
        },
        {
            "comment_id": "UgwZG6CBpMZdEOB70Rp4AaABAg",
            "comment_text": "The people you love are lucky to have you in their lives.",
            "comment_author": "Shelly Hooper",
            "comment_author_id": "UCefvUleIuyPtlZa6CxjuBIQ",
            "comment_time": "2021-09-05T10:30:15+02:00"
        },
        {
            "comment_id": "UgyiTY8W1ccTyfQniwp4AaABAg",
            "comment_text": "Was ist dein Lieblingstier? Meins ist Bacon.",
            "comment_author": "Grosser Manitu",
            "comment_author_id": "UC0fulxjah2qMIWVXGZ5MheA",
            "comment_time": "2021-09-24T06:12:37+02:00"
        }
    ]
}