{
    "video_id": "tSvkoty4YRY",
    "title": "Draches Meinung #018 Mundharmonika",
    "description": "Kanalmitglied werden und exklusive Vorteile erhalten:\nhttps:\/\/www.youtube.com\/channel\/UCm3_j4RLEzgMovQTRPx47MQ\/join\n\nAmazon Liste:\nhttps:\/\/www.amazon.de\/hz\/wishlist\/ls\/2L8FP7DFBFEC7?ref_=wl_share\n\nSoziale Netzwerke___________________________________________________\n\nTikTok:  https:\/\/www.tiktok.com\/@drachenlordrw?lang=de\n\nTwitter https:\/\/twitter.com\/Drachen26328829\n\nSpotifay: https:\/\/open.spotify.com\/artist\/32NwB52qRB6AqswORCxOpV\n\n \u25ba Danke f\u00fcrs anschauen!\n      Gru\u00df\n      Drache",
    "publish_date": "2021-08-25T13:30:15+02:00",
    "duration": "426",
    "channel_id": "UCm3_j4RLEzgMovQTRPx47MQ",
    "channel_title": "Drachen Lord",
    "comments": [
        {
            "comment_id": "UgysmNHHY5MNpO5i_0F4AaABAg",
            "comment_text": "Nimmst du die mit in den Knast?",
            "comment_author": "Kenny",
            "comment_author_id": "UCTH2PzDp5DFaNugaxbQeo2w",
            "comment_time": "2021-08-25T13:31:35+02:00"
        },
        {
            "comment_id": "UgzmGjek2DzLYaizwWR4AaABAg",
            "comment_text": "Kommst du wirklich ins Gef\u00e4ngnis? O.o",
            "comment_author": "Erdbeerchen 1510",
            "comment_author_id": "UC-sU6-weSFCpW_P4uybciWg",
            "comment_time": "2021-08-25T13:32:24+02:00"
        },
        {
            "comment_id": "UgyicGfOeqnnzV9fJSZ4AaABAg",
            "comment_text": "Gru\u00df an die Froindin aus Denken!",
            "comment_author": "Rainer Episch",
            "comment_author_id": "UCssIM7O0YEHXjGIcBwgc-pQ",
            "comment_time": "2021-08-25T13:32:35+02:00"
        },
        {
            "comment_id": "Ugx43akKFJMiBM22b_x4AaABAg",
            "comment_text": "Macht dein Loch auch T\u00f6ne wenn du dir den Luan reinballerst?",
            "comment_author": "Rotaermel",
            "comment_author_id": "UCz6Z53snP-ZVKEk1ykUUJZQ",
            "comment_time": "2021-08-25T13:33:34+02:00"
        },
        {
            "comment_id": "Ugzdny4vvY7Inp19yrl4AaABAg",
            "comment_text": "Deine Schicht scheint diesmal echt lange gewesen zu sein",
            "comment_author": "EA",
            "comment_author_id": "UCEyfTylhK5Xa96o7E51hZiQ",
            "comment_time": "2021-08-25T13:33:38+02:00"
        },
        {
            "comment_id": "UgxS3DZFzLehAns9RdJ4AaABAg",
            "comment_text": "Bist du der echte?",
            "comment_author": "schmomu",
            "comment_author_id": "UCUmkdKGjFVeTr3lScUidE8A",
            "comment_time": "2021-08-25T13:34:41+02:00"
        },
        {
            "comment_id": "Ugy3c51IblwXklbBhFB4AaABAg",
            "comment_text": "Rewiew von saife von bodne aufheben \nJetzt !!",
            "comment_author": "RuherainerRuhe",
            "comment_author_id": "UCMnzzVzEG4GLPKjDh7n4Khw",
            "comment_time": "2021-08-25T13:36:38+02:00"
        },
        {
            "comment_id": "UgzCXYw3qR_YmQaEQtR4AaABAg",
            "comment_text": "Gr\u00fc\u00dfe gehen raus an alle Unterkiefer aus Renken.",
            "comment_author": "Mailo",
            "comment_author_id": "UColAd2r__sDttLI7r9ZXicw",
            "comment_time": "2021-08-25T13:36:41+02:00"
        },
        {
            "comment_id": "Ugxrrn-7DTbSszshTm54AaABAg",
            "comment_text": "Damit kannst du dir im Knast dann wunderbar die Zeit vertreiben. Da k\u00f6nnen dir die W\u00e4rter dann ein kleines St\u00e4ndchen spielen w\u00e4rend du auf Steinen rummeddelst (y)",
            "comment_author": "Markus Brandhuber",
            "comment_author_id": "UCgqDQENp_mTB3lnG1r0MbZA",
            "comment_time": "2021-08-25T13:37:50+02:00"
        },
        {
            "comment_id": "UgzKVQrCO0cwbqztO7V4AaABAg",
            "comment_text": "Doppelmoral in Person",
            "comment_author": "Mr Dollar-Vibe",
            "comment_author_id": "UCPSwPdgOXSZM1K3VXHaDefg",
            "comment_time": "2021-08-25T13:38:13+02:00"
        },
        {
            "comment_id": "UgwTvBkyivq1lr0jgvx4AaABAg",
            "comment_text": "Wann tut die Justiz etwas und beantragt eine Zwangseinweisung in eine geschlossene Heilanstalt",
            "comment_author": "Monika Stahl",
            "comment_author_id": "UCznBQxSXnmJ8CYg5Jm2xdvw",
            "comment_time": "2021-08-25T13:40:10+02:00"
        },
        {
            "comment_id": "UgwCvdCLzLDfHAsoF1t4AaABAg",
            "comment_text": "K\u00f6nnen wir heute wieder einen vlog kriegen wo du mit haidern nett redest?",
            "comment_author": "BONEZ MC",
            "comment_author_id": "UC3eyElQep9oA8rnPH1V5AMQ",
            "comment_time": "2021-08-25T13:41:01+02:00"
        },
        {
            "comment_id": "UgyR7RH3XXUHHWJ5Mmt4AaABAg",
            "comment_text": "Hey bin neu hier!\n Stimmt es, dass du dein Pferd totgefickt hast?",
            "comment_author": "asCension",
            "comment_author_id": "UCecCOWoGr2TL58l-Qt1cGiQ",
            "comment_time": "2021-08-25T13:41:26+02:00"
        },
        {
            "comment_id": "Ugxy7ymlg62RCFoHsxl4AaABAg",
            "comment_text": "Geh zum Supertalent",
            "comment_author": "Versage Phone",
            "comment_author_id": "UCBA6Bvu1Klj2DqEyjDhlEZQ",
            "comment_time": "2021-08-25T13:42:40+02:00"
        },
        {
            "comment_id": "Ugz-hQMjXJu2nDMmUpR4AaABAg",
            "comment_text": "Ist deine Freundin aus Denken wieder weg?",
            "comment_author": "Eazy Kr\u00fcger",
            "comment_author_id": "UCXe_k_Jnaxt5yhaogouWD2w",
            "comment_time": "2021-08-25T13:43:32+02:00"
        },
        {
            "comment_id": "UgwVv40pH3rXhC7BdI54AaABAg",
            "comment_text": "Marmor Stein und Eisen bricht...\nAber unser Oger nicht",
            "comment_author": "Julian Holzer",
            "comment_author_id": "UCjmIeyoFSmE1WvVEOAvYEPQ",
            "comment_time": "2021-08-25T13:43:44+02:00"
        },
        {
            "comment_id": "Ugy-Z56BD5KX9EBwItJ4AaABAg",
            "comment_text": "Andere spielen Mundharmonika, Reinerle hat Mundhare von da Monika (seiner Froindin aus denken dads\u00e4chlich)",
            "comment_author": "Maxx 2853",
            "comment_author_id": "UC_3VmeZW3gdMTXR5U46d1tQ",
            "comment_time": "2021-08-25T13:43:56+02:00"
        },
        {
            "comment_id": "UgwuG5zrFEGgXCJ8R_J4AaABAg",
            "comment_text": "Ich liebe das Format, so nah werden wir nicht mehr an Brojeggd Brote und Br\u00f6tchen kommen, bis er Fr\u00fchst\u00fccksstreams aus der Gef\u00e4ngniskantine macht!",
            "comment_author": "bulliger_barrenschnorrer1510",
            "comment_author_id": "UCAlL5HVc9R9PBvroLVutdUQ",
            "comment_time": "2021-08-25T13:44:56+02:00"
        },
        {
            "comment_id": "UgzyIjDw-yl734sAgN14AaABAg",
            "comment_text": "DieMundharmonika ist nicht auf C, sie startet beim Ton C - weisst du \u00fcberhaupt irgendwas?",
            "comment_author": "Eternal Sloth",
            "comment_author_id": "UCcdU_sMkn7f1rxVB8AYpePA",
            "comment_time": "2021-08-25T13:47:10+02:00"
        },
        {
            "comment_id": "UgwwN3y3-GVbRuXwqlR4AaABAg",
            "comment_text": "Psychisch komplett am Ende der Winkler",
            "comment_author": "Retsch Martin",
            "comment_author_id": "UCDJTd6QgC1WCiB4jgJCNaXQ",
            "comment_time": "2021-08-25T13:48:30+02:00"
        },
        {
            "comment_id": "Ugz3Kx754vFYn0PemrF4AaABAg",
            "comment_text": "Da kriegt man direkt Lust ihm etwas aus seiner Amazon-Wunschliste zu bestellne!",
            "comment_author": "Umayyad",
            "comment_author_id": "UCsUlmvKY43Kgk4M2gcq7o0A",
            "comment_time": "2021-08-25T13:50:33+02:00"
        },
        {
            "comment_id": "UgzXLD8JsJZLtoB0Sv14AaABAg",
            "comment_text": "Jetzt wo er alles macht kann er doch immer als Ein-Mann-Orchester zum Tor Gehen und Krach machen so kann er \u00dcben und die Leute \u00dcbert\u00f6nen eine Win Win sitoation xD &lt;3",
            "comment_author": "Noir Horo",
            "comment_author_id": "UCVV0mh_tHbRwxjCtb_k90AQ",
            "comment_time": "2021-08-25T13:50:35+02:00"
        },
        {
            "comment_id": "UgzdTal5-gghZ20vz5p4AaABAg",
            "comment_text": "Kommt mal wieder ein Gummibubbn Fergewaldiguks Fideo oder so ?",
            "comment_author": "BIack0ut23",
            "comment_author_id": "UCL-awbtVpE3mnKQnR4924Zw",
            "comment_time": "2021-08-25T13:51:06+02:00"
        },
        {
            "comment_id": "Ugx-aG6GgrQ9vp3mTEl4AaABAg",
            "comment_text": "Wie indelekduel und gebildet er aufem ThumbNeil aussiehtne. Trozdem pr\u00e4chdiges Format. 15\/10 Ofenk\u00e4sne",
            "comment_author": "PR Performance",
            "comment_author_id": "UCeZo3yMsJRTnGprgYWsKObQ",
            "comment_time": "2021-08-25T13:52:59+02:00"
        },
        {
            "comment_id": "UgwWnLwOkA12ZGQR-514AaABAg",
            "comment_text": "Draches Meinung, aber im thumbnail steht objektiv... Wie kann eine Meinung objektiv sein, eine eigene meinung ist subjektiv du pfosten",
            "comment_author": "Dominik Ist Toll",
            "comment_author_id": "UCAlHI2QWxWx0QCxegcQeuCQ",
            "comment_time": "2021-08-25T13:53:43+02:00"
        },
        {
            "comment_id": "UgxvQKxqDhbhB3siaHZ4AaABAg",
            "comment_text": "Der Meinungslord am start meddel leude",
            "comment_author": "Bxni.55",
            "comment_author_id": "UCLyt9uTh_hThwFq49PN3gTw",
            "comment_time": "2021-08-25T13:54:19+02:00"
        },
        {
            "comment_id": "UgxTdI2srTRxJm2-Ge14AaABAg",
            "comment_text": "&quot;Man kann es gut lernen, wenn man zwei, drei Stunden am Tag \u00fcbt.&quot; Er begreift immer noch nicht, dass andere Leute ARBEITEN gehen.",
            "comment_author": "Bielefeld und mehr",
            "comment_author_id": "UCMqkWb8iTYdGWnCY9t2O3Uw",
            "comment_time": "2021-08-25T13:56:27+02:00"
        },
        {
            "comment_id": "UgylT0B0KQe1xzjoGI94AaABAg",
            "comment_text": "Was kannst du eigentlich? Versuche doch der Gesellschaft zumindest teilweise n\u00fctzlich zu sein, du Ignorant.",
            "comment_author": "Umayyad",
            "comment_author_id": "UCsUlmvKY43Kgk4M2gcq7o0A",
            "comment_time": "2021-08-25T13:56:28+02:00"
        },
        {
            "comment_id": "Ugy7DVfuxFmIyDNqI7V4AaABAg",
            "comment_text": "Im Prinzip ist es recht einfach. Eine Mundharmonika zu spielen ist sehr einfach, denn es ist sehr einfach",
            "comment_author": "Darth Kronos",
            "comment_author_id": "UCHM5KFidhiJIG7U6dY5VLZA",
            "comment_time": "2021-08-25T13:57:23+02:00"
        },
        {
            "comment_id": "UgzGovtGNe363Pdwzyd4AaABAg",
            "comment_text": "Bestes Instrument f\u00fcr den Knast!",
            "comment_author": "Aileen Freidank",
            "comment_author_id": "UCXHa5WHJXiYKkZu6wj48NnA",
            "comment_time": "2021-08-25T13:57:58+02:00"
        },
        {
            "comment_id": "UgxG7_E06nqEJHioyWp4AaABAg",
            "comment_text": "Meinung zu Coroner w\u00fcrde mich brennend interessieren.",
            "comment_author": "Bucklige Brotspinne",
            "comment_author_id": "UC3t7UDZKNpRFtWDQsY6bkIQ",
            "comment_time": "2021-08-25T14:00:13+02:00"
        },
        {
            "comment_id": "UgxXpxByANp5Ui72JEZ4AaABAg",
            "comment_text": "Genau Tonerzeugung bei anderen Instrumenten ist unm\u00f6glich:\nGitarre:           6 j\u00e4hriges Studium, ansonsten kommt da kein Ton raus\nSchlagzeug:   Mindestens 1 Jahr GYM ansonsten bleibt das Schlagzeug still\n\nAber die Mundharmonika, mit der kann jeder umgehen, auch Menschen mit Asthma",
            "comment_author": "Hexla -",
            "comment_author_id": "UCpUNCWKB801Iui-asa4WIoQ",
            "comment_time": "2021-08-25T14:01:43+02:00"
        },
        {
            "comment_id": "UgzPmk5SCN4eFCEmI0l4AaABAg",
            "comment_text": "Wie geht es deinem Sohn???",
            "comment_author": "Erich Honecker",
            "comment_author_id": "UCGm0AnXkUXIOP1_u2M68qqw",
            "comment_time": "2021-08-25T14:05:54+02:00"
        },
        {
            "comment_id": "Ugxh2VVQseCdzNwnqAZ4AaABAg",
            "comment_text": "Gef\u00e4llt dir die neue Bodenfarbe auf deinem Grundst\u00fcck ?",
            "comment_author": "Billy Corgan",
            "comment_author_id": "UCzQOTfryzo2vXvB_tVZwiyg",
            "comment_time": "2021-08-25T14:06:31+02:00"
        },
        {
            "comment_id": "Ugw-JGHqmIbo94baZzp4AaABAg",
            "comment_text": "Die Mundamoniga",
            "comment_author": "Haha haha",
            "comment_author_id": "UCGKYnaJXK4BlMet_3gG1jlQ",
            "comment_time": "2021-08-25T14:07:06+02:00"
        },
        {
            "comment_id": "UgyklW3ghX7aiCHszm94AaABAg",
            "comment_text": "Du kannst das lied nicht mehr spielen? du hast niemals dises lied gelernt (klassisches L\u00fcL\u00fcL\u00fc) . Man, aller, deine Geltungssucht ist so durchschaubar.\nIch gehe mal davon aus, dass, wenn man ein Lied mal spielen konnte, es auch im fortgeschrittenen Alter noch spielen kann. Es gibt Berichte von Demenz erkannten Menschen die im Zustand ihrer Krankheit noch lieder spielen, die sie im Kindesalter gelernt haben.",
            "comment_author": "Herr OLF",
            "comment_author_id": "UCahKWMneIMt1_NFaGGXFdMQ",
            "comment_time": "2021-08-25T14:08:23+02:00"
        },
        {
            "comment_id": "Ugwsm2pTWzLB0sNC4LN4AaABAg",
            "comment_text": "Was is des alda. Ich kriege keine Benachrichtigungne bei youtub",
            "comment_author": "Johnny Splash",
            "comment_author_id": "UCwT7yAUlvg9Km2xptUuEZlQ",
            "comment_time": "2021-08-25T14:11:20+02:00"
        },
        {
            "comment_id": "UgxefpMJf6Dyb_Xvbdx4AaABAg",
            "comment_text": "Lord? Du bist 32 und noch Jungfrau!",
            "comment_author": "Erich Honecker",
            "comment_author_id": "UCGm0AnXkUXIOP1_u2M68qqw",
            "comment_time": "2021-08-25T14:11:56+02:00"
        },
        {
            "comment_id": "UgzhO9dy8_wKZoRbq4V4AaABAg",
            "comment_text": "MEINUNGSVIDEO \u00dcBER KLOPAPIER BITTE",
            "comment_author": "Simon",
            "comment_author_id": "UCyb1FBiE_cBrNJCLeBY45Bg",
            "comment_time": "2021-08-25T14:15:49+02:00"
        },
        {
            "comment_id": "UgyVPG9SB0wRu_d9YYx4AaABAg",
            "comment_text": "\u00dcb mal paar Gef\u00e4ngnislieder",
            "comment_author": "Ivan Red",
            "comment_author_id": "UCfegxYeHIunEfQIrHVs9HUQ",
            "comment_time": "2021-08-25T14:18:11+02:00"
        },
        {
            "comment_id": "UgwsnjMcxNNxbUN7IqN4AaABAg",
            "comment_text": "Ey was babbelt mich eigentlich ein Typ voll, der noch nie ein Instrument wirklich gespielt hat oder jemals Noten gelesen hat?",
            "comment_author": "Patti",
            "comment_author_id": "UCbSzYYAJtW3nGzIAFEk8wIQ",
            "comment_time": "2021-08-25T14:25:46+02:00"
        },
        {
            "comment_id": "Ugw3Ph3phW95gmNt2yd4AaABAg",
            "comment_text": "Der n\u00e4chsde Michael Hirdde tadsechlich sogar.",
            "comment_author": "marcb_aus_f",
            "comment_author_id": "UC5q7UBJukUGtsk4MxvQJ6dA",
            "comment_time": "2021-08-25T14:26:38+02:00"
        },
        {
            "comment_id": "UgxmgWZJMsVb85dYJ6p4AaABAg",
            "comment_text": "Die arme Mundharmonika ????",
            "comment_author": "W B",
            "comment_author_id": "UCag9BVxO7_3jePlCy0YF75g",
            "comment_time": "2021-08-25T14:26:42+02:00"
        },
        {
            "comment_id": "Ugzp9f6xxQnm8lyYJFF4AaABAg",
            "comment_text": "Mit 4 Jahren schon mit Free Willy im Wald die Monika mit dem Mund harmonisch geblasen, aller. Und weider?",
            "comment_author": "MoeSeineTaverne",
            "comment_author_id": "UCqOyQLK2QoobhRI9E2qwS_w",
            "comment_time": "2021-08-25T14:41:46+02:00"
        },
        {
            "comment_id": "UgzdCxCS3CeRvRlYmy94AaABAg",
            "comment_text": "Es heisssd muntermonika",
            "comment_author": "KotzenderKeks",
            "comment_author_id": "UCFa2lxnt6Mnk2XRZmgizRfg",
            "comment_time": "2021-08-25T14:42:41+02:00"
        },
        {
            "comment_id": "Ugxfz_8wMnQ84kt-VJl4AaABAg",
            "comment_text": "HERR WINKLER Wahltag ist bald.\nIch wei\u00df nicht welche Partei.\nBrauche ihre Meinung.",
            "comment_author": "Mr Kater",
            "comment_author_id": "UCkj-ozffjrStVdLJBphP_Gg",
            "comment_time": "2021-08-25T14:42:53+02:00"
        },
        {
            "comment_id": "UgyqApSFzLXp6mWkX-B4AaABAg",
            "comment_text": "Reinerle und sein Goschenhobel, ich schnall ab...........................",
            "comment_author": "Meteo Shark",
            "comment_author_id": "UCTL1UCsP5-TJOA7MdM14nxQ",
            "comment_time": "2021-08-25T14:42:59+02:00"
        },
        {
            "comment_id": "UgzbU6oJLnj23GIjSlR4AaABAg",
            "comment_text": "Wir wissen bereits von deinem Zeugnis, dass du einfache Aufgaben nach einer sehr ausf\u00fchrlichen Einarbeitungszeit ausf\u00fchren kannst.",
            "comment_author": "Simon",
            "comment_author_id": "UCyb1FBiE_cBrNJCLeBY45Bg",
            "comment_time": "2021-08-25T14:50:31+02:00"
        },
        {
            "comment_id": "Ugw-wUQFAbLRRzuBrbR4AaABAg",
            "comment_text": "Spiel und doch mal was vor!",
            "comment_author": "PaPaBenschi",
            "comment_author_id": "UCQw2WgZLkwIkjsC5AzJxXfg",
            "comment_time": "2021-08-25T15:48:53+02:00"
        },
        {
            "comment_id": "UgwHLI786jMxryzBEwB4AaABAg",
            "comment_text": "Jene versteckten Nachrichten auf der Mundharmonika, wunderbar!",
            "comment_author": "TheK0kett",
            "comment_author_id": "UCS9i4V4_iqXQuMu28M3n9XA",
            "comment_time": "2021-08-25T16:15:53+02:00"
        },
        {
            "comment_id": "UgykNGGQ6RgSibBgY254AaABAg",
            "comment_text": "* Ihm mal ein paar Provokantje hinwirft * Zumindest kann er Mundharmonika schreiben und wei\u00df wohl was Harmonie Mundt\u00f6ne und Atem so ausmachen. * und wann zeigt er Dir die Breitmaulfroschsammlung? * Seit wann gibts denn sowas? Toll.",
            "comment_author": "Viola Sch\u00fcmann",
            "comment_author_id": "UCYIACU0HByF02616NWYBWMg",
            "comment_time": "2021-08-25T16:50:04+02:00"
        },
        {
            "comment_id": "Ugz1IIIkDCTnmuOP5eN4AaABAg",
            "comment_text": "Ich find es super das du schon eine Mundharmonika f\u00fcr den Knast parat hast. Vielleicht solltest du deine restliche Zeit zum spielen \u00fcben nutzen anstatt sie mit dummen Videos zu verschwenden.",
            "comment_author": "Lil",
            "comment_author_id": "UCUaIb4aPolc1Vph56gN8WiA",
            "comment_time": "2021-08-25T16:57:05+02:00"
        },
        {
            "comment_id": "Ugy4Q4bRsZ9Ueu2YP_h4AaABAg",
            "comment_text": "irgendwie spielen alle versager mundharmonika",
            "comment_author": "JAzu MDMA",
            "comment_author_id": "UCibDpNQ5XnDalULuJk40iOw",
            "comment_time": "2021-08-25T17:14:08+02:00"
        },
        {
            "comment_id": "Ugx_S2cWs-z665sInYR4AaABAg",
            "comment_text": "Wie er seit Gestern immer noch &quot;Kr\u00fcmel&quot; auf dem T-Sch\u00f6rder hat",
            "comment_author": "MonsteraX11",
            "comment_author_id": "UCxQLCRCkubFlKzxCH2t_KlQ",
            "comment_time": "2021-08-25T17:40:59+02:00"
        },
        {
            "comment_id": "Ugy3f_Xk-LSj_Rtbw6R4AaABAg",
            "comment_text": "Ich spiele Mundharmonika nicht, weil es cool ist. Ich spiele Mundharmonika, weil ich gerne Mundharmonika spiele.\n\nAbgesehen davon spiele ich keine Mundharmonika.",
            "comment_author": "Martin Neumann",
            "comment_author_id": "UCMW_j-uVV03seHoYSx4sZ6Q",
            "comment_time": "2021-08-25T17:41:47+02:00"
        },
        {
            "comment_id": "Ugz0pP1T04YRGBgzuj54AaABAg",
            "comment_text": "Das hat immer noch NICHTS mit deiner Meinung zutun. Das was du da machst ist eine Beschreibung.",
            "comment_author": "MonsteraX11",
            "comment_author_id": "UCxQLCRCkubFlKzxCH2t_KlQ",
            "comment_time": "2021-08-25T17:44:29+02:00"
        },
        {
            "comment_id": "UgxxMo0yo0jMLJ3pMoB4AaABAg",
            "comment_text": "Gibt es \u00fcberhaupt ein Video, in dem der Lord ein sauberes Kleidungsst\u00fcck tr\u00e4gt?",
            "comment_author": "Hans Hart",
            "comment_author_id": "UC_cCerVmspXlU7SuhPlOdOg",
            "comment_time": "2021-08-25T18:20:14+02:00"
        },
        {
            "comment_id": "UgydKBGaLNt9DMqKJQ94AaABAg",
            "comment_text": "Danke! Jetzt hab ich wieder n Video das ich verlinken kann wenn mich jemand fragt &quot;warum sagen alle, der Drachenlord sei so dumm?&quot;.",
            "comment_author": "Drachenliebe",
            "comment_author_id": "UCMGbWUQRtimCzqI5zHBfqKg",
            "comment_time": "2021-08-25T18:34:39+02:00"
        },
        {
            "comment_id": "Ugy4iX7DFVPYGjNcXQN4AaABAg",
            "comment_text": "Das einzige Instrument, welches du je ann\u00e4hernd beherrscht hast, d\u00fcrfte die Triangel in der Dulliakademie gewesen sein.",
            "comment_author": "Old Wankerhand",
            "comment_author_id": "UCiTmfuuO0uVCq_eZar0fVcg",
            "comment_time": "2021-08-25T18:38:28+02:00"
        },
        {
            "comment_id": "UgzBlPz-UlwW61_5-v54AaABAg",
            "comment_text": "Dange Drache f\u00fcr die aufklerung, du spilst ja suber mondamonika tadsechlig",
            "comment_author": "Jan Hesse",
            "comment_author_id": "UCqrRgDGqLNJEwOTsqnZqRZw",
            "comment_time": "2021-08-25T18:50:13+02:00"
        },
        {
            "comment_id": "UgzLpiSsZQGrVSIkBvV4AaABAg",
            "comment_text": "&quot;Mundharmonika&quot; hatter safe im Dudne nachgegugld.",
            "comment_author": "Alf92",
            "comment_author_id": "UC9CzSnyiWMqIkvv43MwiOzQ",
            "comment_time": "2021-08-25T20:20:08+02:00"
        },
        {
            "comment_id": "UgxzCS0nItk6PEjK6Ml4AaABAg",
            "comment_text": "Er hat schon mit 4 Jahren im Wald Mundharmonika gespielt",
            "comment_author": "Mieki",
            "comment_author_id": "UCMePM4ocDQPAjl_dStb3UDg",
            "comment_time": "2021-08-25T20:48:02+02:00"
        },
        {
            "comment_id": "Ugxz7IZbgiGlF_njifh4AaABAg",
            "comment_text": "Die Klicks gehen durch die Decke, bitte lad doch noch ein paar mehr Videos pro Tag hoch",
            "comment_author": "KEMO",
            "comment_author_id": "UC78nNnyoXrzWPvMjqyss1_g",
            "comment_time": "2021-08-25T21:28:30+02:00"
        },
        {
            "comment_id": "UgzQ9yQLjM-7PqZKHi94AaABAg",
            "comment_text": "Oh Gott mich als Mundharmonika Spieler Kratzen alle N\u00e4gel wenn er anf\u00e4ngt zu spielen ????????",
            "comment_author": "Omega Z.",
            "comment_author_id": "UCGqHN1e5euHIGEYdPpzB-9A",
            "comment_time": "2021-08-25T22:05:13+02:00"
        },
        {
            "comment_id": "Ugyz_mXJbvrskDbjsYV4AaABAg",
            "comment_text": "Mudda Monika",
            "comment_author": "Ndouble H P",
            "comment_author_id": "UC4oFsWlCrzeJYleKjLR1Fkg",
            "comment_time": "2021-08-25T23:42:29+02:00"
        },
        {
            "comment_id": "UgyHtHuuZNvTf8GzVup4AaABAg",
            "comment_text": "Was Index, ich mache dich munter, Monika\nDu kommst mit Mundharmonika, ich im Mund der Monika",
            "comment_author": "YT Unbekannter Nummer 2",
            "comment_author_id": "UCAHYQ-6Hv7S0Pa8qkqKWxZQ",
            "comment_time": "2021-08-26T00:19:28+02:00"
        },
        {
            "comment_id": "UgxHPSO5S4TfBNxEG6R4AaABAg",
            "comment_text": "Er hat schon damals Mundharmonika gespielt.\nDie hatte aber nur zwei \u00d6ffnungen, und nannte sich Trillerpfeife tadsechlich soga",
            "comment_author": "A.S. Cirillo",
            "comment_author_id": "UCew5oKvLBIq4rVy4R4-FExQ",
            "comment_time": "2021-08-26T01:39:02+02:00"
        },
        {
            "comment_id": "Ugy3BBM6mHuYeRDZ4Uh4AaABAg",
            "comment_text": "Wir wolln\u00f6h, sehn\u00f6h, wie dun\u00f6h \u00fcber deinen schrarzn\u00f6h luan\u00f6h redest undn\u00f6h in die kameran\u00f6h haltn\u00f6h. Liken\u00f6h damitn\u00f6h er das siehtn\u00f6h.",
            "comment_author": "BUDDHAALIEN",
            "comment_author_id": "UCyayy7IK_fUhc5SkvogjXdg",
            "comment_time": "2021-08-26T03:01:52+02:00"
        },
        {
            "comment_id": "Ugwks4NGAfFFTG-Wlxh4AaABAg",
            "comment_text": "Mein Froindin hat auch 2 T\u00f6ne pro Loch.",
            "comment_author": "Ferd Blu",
            "comment_author_id": "UCgaqkSOlZmAguchwddqYhyw",
            "comment_time": "2021-08-26T03:02:21+02:00"
        },
        {
            "comment_id": "UgxLlj_b_fkIPu_ukRN4AaABAg",
            "comment_text": "Warum redest du nichtn\u00f6h \u00fcber dien\u00f6h Haggebudtn\u00f6h ?",
            "comment_author": "BUDDHAALIEN",
            "comment_author_id": "UCyayy7IK_fUhc5SkvogjXdg",
            "comment_time": "2021-08-26T03:02:53+02:00"
        },
        {
            "comment_id": "UgyH9WK8qcgW6bAYlIR4AaABAg",
            "comment_text": "4:40 der blick sieht aus als w\u00fcrde er sein leben hinterfragen und den Gedanken mit den worten &quot;egal, hauptsache die wunschliste wird gekauft&quot; abschlie\u00dft.",
            "comment_author": "Papa Punchline",
            "comment_author_id": "UCDZ8h5hZ61iHSzyF6d5Wmfw",
            "comment_time": "2021-08-26T04:05:47+02:00"
        },
        {
            "comment_id": "Ugxf1CtsVJlBMVT2pYB4AaABAg",
            "comment_text": "Wenn es Dir so wichtig ist, andere nicht zu st\u00f6ren, dann schalte Deine verdammte Alarmanlage aus, die den ganzen Ort beschallt und nervt.",
            "comment_author": "Leopard Prince",
            "comment_author_id": "UCXIP7MMMl0TJUl4yNpJlm-Q",
            "comment_time": "2021-08-26T08:37:50+02:00"
        },
        {
            "comment_id": "Ugz-e5FOs0z1ptGOJnx4AaABAg",
            "comment_text": "Wie immer 110% wortgulasch...",
            "comment_author": "ThinkUpOut",
            "comment_author_id": "UCyzLb0x3EPGPlD02_OKq_0w",
            "comment_time": "2021-08-26T10:14:01+02:00"
        },
        {
            "comment_id": "UgwA3sEfhAMFjyvn0KR4AaABAg",
            "comment_text": "kann nicht mal spielen auf dem ding...l\u00fcl\u00fcl\u00fcgenlord",
            "comment_author": "jo rein",
            "comment_author_id": "UCKN68YrfsVhm7gRRQZvFJRQ",
            "comment_time": "2021-08-26T10:59:58+02:00"
        },
        {
            "comment_id": "UgwJTu0bKeem4ftIfDl4AaABAg",
            "comment_text": "Zahnstein sein Vadder. Putz mal deine Z\u00e4hne",
            "comment_author": "Ezechiel Goldstein",
            "comment_author_id": "UCGEMhiY8li-QZZiRpsOEuMQ",
            "comment_time": "2021-08-26T11:24:12+02:00"
        },
        {
            "comment_id": "UgxK53Ex0P3ak3bTM314AaABAg",
            "comment_text": "Wieder unglaublich was der Multiinstrumentalversager da wieder abl\u00e4sst!",
            "comment_author": "Kokosflocken St\u00e4nder",
            "comment_author_id": "UCkI8GQKNs3k0WynR8a3fZHg",
            "comment_time": "2021-08-26T11:40:33+02:00"
        },
        {
            "comment_id": "UgzW7XX0goTAH5aQW0Z4AaABAg",
            "comment_text": "deutschland komplett degeneriert und grenzdebil...passt.-",
            "comment_author": "XingXsi",
            "comment_author_id": "UCrecs5mhd6Xy7zHIT-1ygAg",
            "comment_time": "2021-08-26T12:36:15+02:00"
        },
        {
            "comment_id": "UgzJbYpFWnrtR7_PRSB4AaABAg",
            "comment_text": "Nach Brot und Br\u00f6tchen sein bestes Projekt.\n\n\n\n\n\nDanke daf\u00fcr Iblali",
            "comment_author": "alien proteom",
            "comment_author_id": "UCg3DCPnLLE_dxI1Z0gUumOg",
            "comment_time": "2021-08-26T23:25:31+02:00"
        },
        {
            "comment_id": "UgxzS-K2YayA6zsalwt4AaABAg",
            "comment_text": "Du hast von Musik und Musikinstrumenten keine Ahnung. Du redest sehr wirres Zeug bez\u00fcglich der T\u00f6ne. Begriffe, die du nicht kennst sind C-Dur und das ist kein einzelner Ton sondern setzt sich aus mehreren T\u00f6nen zusammen, mit C-Dur ist in diesen Fall eine Tonleiter gemeint. Eine C-Dur gestimmte Richter-Mundharmonika hat folgende T\u00f6ne: C, D, E, F, G, A und B. Du redest hier nur Schwachsinn zusammen aber Leute, die dich bezahlen, glauben dir das bestimmt und wenn nicht, bannst du Sie weg. Du machst den Leuten wieder was vor und das ist unehrlich!",
            "comment_author": "Pandemik",
            "comment_author_id": "UCe0qVwkwXqOeSMAP-HJVM5g",
            "comment_time": "2021-08-26T23:36:43+02:00"
        },
        {
            "comment_id": "Ugxoy1TIGB5wtoL9DWR4AaABAg",
            "comment_text": "Spiel mir das Lied vom Diabetes-Tod.",
            "comment_author": "Beteigeuze",
            "comment_author_id": "UCywuwF_ff5y4__dBKrdGEEA",
            "comment_time": "2021-08-27T02:10:20+02:00"
        },
        {
            "comment_id": "UgyN8ByG6xVeoz8Xkqx4AaABAg",
            "comment_text": "Fr\u00fcher konnde er das Lied aus Free Willy auf der Mundharmonigga spielen, heude hatter das Gewicht von Free Willy, tadz\u00e4chlich sogar.",
            "comment_author": "Spikeyfied",
            "comment_author_id": "UCUKEllyCChoO4AiB99kzM9g",
            "comment_time": "2021-08-27T15:28:24+02:00"
        },
        {
            "comment_id": "UgyzmroJ9ZHSEXq2AX94AaABAg",
            "comment_text": "was f\u00fcr eine sch\u00f6ne melodei",
            "comment_author": "change_profile_n",
            "comment_author_id": "UCkPybLOpEtWh23uWC733AYw",
            "comment_time": "2021-08-27T16:14:28+02:00"
        },
        {
            "comment_id": "UgxEvDtlWvg-NR7zx-J4AaABAg",
            "comment_text": "Gutes Tonerzeugungsk\u00f6nnen",
            "comment_author": "Nasserfart Abou Kaka",
            "comment_author_id": "UCCV_LjRq0p4VuYRLp91Ki8w",
            "comment_time": "2021-08-27T17:29:09+02:00"
        },
        {
            "comment_id": "Ugyap84pMbqNCk1AZUd4AaABAg",
            "comment_text": "F\u00fcr mich ein super Instrument. Erinnert mich total an meine Kindheit",
            "comment_author": "Blackpatty1992",
            "comment_author_id": "UCYjjBYNqTOtCZpU9qt3qIbg",
            "comment_time": "2021-08-27T18:05:24+02:00"
        },
        {
            "comment_id": "UgxsTSEfSIh8hUtVOZN4AaABAg",
            "comment_text": "Die ber\u00fchmte Muttermonika",
            "comment_author": "gizmo",
            "comment_author_id": "UC5zvf9hbtWW8CdXZJuQgWKw",
            "comment_time": "2021-08-30T07:28:15+02:00"
        },
        {
            "comment_id": "Ugz5GsJhpdawhw1RqFF4AaABAg",
            "comment_text": "\ud83d\ude0a",
            "comment_author": "madonnazone",
            "comment_author_id": "UCkjfaPhTejk3a7OML3Dzz9Q",
            "comment_time": "2021-09-12T10:23:07+02:00"
        },
        {
            "comment_id": "UgzrjXP9w3GPfWkMEXt4AaABAg",
            "comment_text": "danke drachenlord ich hatte eine gute zeit mit meiner freundin wegen dir !",
            "comment_author": "Kuramen",
            "comment_author_id": "UCH9XNLgPQ5LFkoZz_5W2G2A",
            "comment_time": "2021-10-25T13:11:35+02:00"
        },
        {
            "comment_id": "UgxE3yiASXQkJcX4Tmp4AaABAg",
            "comment_text": "Also ich kenne Leute die spielen nach dem Treppensteigen immer Mundharmonika. V\u00f6llig ohne Mundharmonika \ud83d\ude02",
            "comment_author": "Ricardo Michalski",
            "comment_author_id": "UC35cHRp94mup0j-94Rq26EQ",
            "comment_time": "2021-12-27T22:58:07+01:00"
        }
    ]
}